{
  "mdezvoltarii": [
    {
      "currentUrl": "https://www.mdlpa.ro/pages/proiectlegemodificarelegea2122022masuririscseismic",
      "date": "22-02-2023",
      "name": "Proiect de LEGE pentru modificarea și completarea Legii nr. 212/2022 privind unele măsuri pentru reducerea riscului seismic al clădirilor",
      "documents": [
        {
          "date": "22-02-2023",
          "link": "https://www.mdlpa.ro/uploads/articole/attachments/63f600500fb57363513933.doc",
          "title": "Proiect de Lege",
          "type": "doc"
        },
        {
          "date": "22-02-2023",
          "link": "https://www.mdlpa.ro/uploads/articole/attachments/63f6004ed6afc907504247.docx",
          "title": "Expunerea de motive",
          "type": "doc"
        }
      ]
    },
    {
      "currentUrl": "https://www.mdlpa.ro/pages/proiectougaprobareprogramnationalscolisigure",
      "date": "22-02-2023",
      "name": "Proiect de OUG pentru aprobarea Programului național „Școli sigure și sănătoase”",
      "documents": [
        {
          "date": "22-02-2023",
          "link": "https://www.mdlpa.ro/uploads/articole/attachments/63f60071b9753748410110.docx",
          "title": "Proiect de Ordonanță de urgență",
          "type": "doc"
        },
        {
          "date": "22-02-2023",
          "link": "https://www.mdlpa.ro/uploads/articole/attachments/63f60071a8778442143619.docx",
          "title": "Nota de fundamentare",
          "type": "doc"
        },
        {
          "date": "22-02-2023",
          "link": "https://www.mdlpa.ro/uploads/articole/attachments/63f60070cc1d3615305469.xlsx",
          "title": "Fișa financiară",
          "type": "xls"
        }
      ]
    },
    {
      "currentUrl": "https://www.mdlpa.ro/pages/proiectordinaprobarereglementareghidconsolidaretalazuricanalediguri",
      "date": "16-02-2023",
      "name": "Proiect de ORDIN pentru aprobarea reglementării tehnice „Ghid pentru proiectarea şi execuţia lucrărilor de protejare şi consolidare a taluzurilor la canale şi diguri, indicativ GE 027-2023”",
      "documents": [
        {
          "date": "16-02-2023",
          "link": "https://www.mdlpa.ro/uploads/articole/attachments/63ee2572b8681849472176.doc",
          "title": "Proiect de Ordin",
          "type": "doc"
        },
        {
          "date": "16-02-2023",
          "link": "https://www.mdlpa.ro/uploads/articole/attachments/63ee25735d187505095248.docx",
          "title": "Anexa",
          "type": "doc"
        },
        {
          "date": "16-02-2023",
          "link": "https://www.mdlpa.ro/uploads/articole/attachments/63ee2572cdce1618810484.doc",
          "title": "Referat de aprobare",
          "type": "doc"
        }
      ]
    },
    {
      "currentUrl": "https://www.mdlpa.ro/pages/proiectordinaprobarereglementareghidzoneinundabile",
      "date": "16-02-2023",
      "name": "Proiect de ORDIN pentru aprobarea reglementării tehnice „Ghid de bune practici privind măsuri de protecție aplicabile clădirilor existente și clădirilor noi, situate în zone inundabile, indicativ RTC 12 - 2023”",
      "documents": [
        {
          "date": "16-02-2023",
          "link": "https://www.mdlpa.ro/uploads/articole/attachments/63ee22c395f21617216144.doc",
          "title": "Proiect de Ordin",
          "type": "doc"
        },
        {
          "date": "16-02-2023",
          "link": "https://www.mdlpa.ro/uploads/articole/attachments/63ee236d7a719728045928.docx",
          "title": "Anexa",
          "type": "doc"
        },
        {
          "date": "16-02-2023",
          "link": "https://www.mdlpa.ro/uploads/articole/attachments/63ee22c3aadb3104096088.doc",
          "title": "Referat de aprobare",
          "type": "doc"
        }
      ]
    },
    {
      "currentUrl": "https://www.mdlpa.ro/pages/proiectordinaprobarereglementareghidzoneinundabilertc11",
      "date": "16-02-2023",
      "name": "Proiect de ORDIN pentru aprobarea reglementării tehnice „Ghid de bune practici privind măsuri de adaptare aplicabile clădirilor existente și clădirilor noi, situate în zone inundabile, indicativ RTC 11 - 2023”",
      "documents": [
        {
          "date": "16-02-2023",
          "link": "https://www.mdlpa.ro/uploads/articole/attachments/63ee24001763a289715358.doc",
          "title": "Proiect de Ordin",
          "type": "doc"
        },
        {
          "date": "16-02-2023",
          "link": "https://www.mdlpa.ro/uploads/articole/attachments/63ee240007b4a043026819.docx",
          "title": "Anexa",
          "type": "doc"
        },
        {
          "date": "16-02-2023",
          "link": "https://www.mdlpa.ro/uploads/articole/attachments/63ee240026caa579204028.doc",
          "title": "Referat de aprobare",
          "type": "doc"
        }
      ]
    },
    {
      "currentUrl": "https://www.mdlpa.ro/pages/proiectougmodificarelegea3152004dezvoltareregionala",
      "date": "16-02-2023",
      "name": "Proiect de OUG pentru modificarea și completarea art. 8 din Legea nr. 315/2004 privind dezvoltarea regională în România",
      "documents": [
        {
          "date": "16-02-2023",
          "link": "https://www.mdlpa.ro/uploads/articole/attachments/63ee15bf0eb17818785158.docx",
          "title": "Proiect OUG",
          "type": "doc"
        },
        {
          "date": "16-02-2023",
          "link": "https://www.mdlpa.ro/uploads/articole/attachments/63ee15bef3f46525575752.docx",
          "title": "Nota de fundamentare",
          "type": "doc"
        },
        {
          "date": "16-02-2023",
          "link": "https://www.mdlpa.ro/uploads/articole/attachments/6407318717986844181291.docx",
          "title": "Registrului pentru consemnarea şi analizarea propunerilor, sugestiilor, opiniilor cu valoare de recomandare primite",
          "type": "doc"
        }
      ]
    },
    {
      "currentUrl": "https://www.mdlpa.ro/pages/proiectordinmasurapsrijinajutoarecursuripnrrc5",
      "date": "16-02-2023",
      "name": "Proiect de ORDIN privind aprobarea Măsurii de sprijin, constând în acordarea unor ajutoare de minimis/ajutoare de stat, pentru cursuri de formare de scurtă durată în domeniul eficienței energetice a cel puțin 8.000 de specialiști și lucrători din sectorul construcțiilor, aferentă investiției I3 “Consolidarea capacității profesionale a specialiștilor și lucrătorilor din domeniul construcțiilor prin dezvoltarea de cursuri de pregătire în renovare energetică”, prevăzută în cadrul Planului național de redresare și reziliență al României 2021-2026, Pilonul I. Tranziție verde, Componenta C5 – Valul renovării, Ținta nr. 109",
      "documents": [
        {
          "date": "16-02-2023",
          "link": "https://www.mdlpa.ro/uploads/articole/attachments/63ee07c1118ea652081850.doc",
          "title": "Proiect de Ordin",
          "type": "doc"
        },
        {
          "date": "16-02-2023",
          "link": "https://www.mdlpa.ro/uploads/articole/attachments/63ee07c0f2417709863346.docx",
          "title": "Anexa",
          "type": "doc"
        },
        {
          "date": "16-02-2023",
          "link": "https://www.mdlpa.ro/uploads/articole/attachments/63ee07c12f3af190310549.doc",
          "title": "Referat de aprobare",
          "type": "doc"
        }
      ]
    },
    {
      "currentUrl": "https://www.mdlpa.ro/pages/proiecthgaprobaretezeprealabilecodadministrativ",
      "date": "16-02-2023",
      "name": "Proiect de HG pentru aprobarea Tezelor prealabile ale proiectului Codului de procedură administrativă",
      "documents": [
        {
          "date": "16-02-2023",
          "link": "https://www.mdlpa.ro/uploads/articole/attachments/63ee063e36e70964939471.DOCX",
          "title": "Proiect HG",
          "type": "doc"
        },
        {
          "date": "16-02-2023",
          "link": "https://www.mdlpa.ro/uploads/articole/attachments/63ee063e29e4c915097347.docx",
          "title": "Anexa",
          "type": "doc"
        },
        {
          "date": "16-02-2023",
          "link": "https://www.mdlpa.ro/uploads/articole/attachments/63ee063e45cf6072092845.docx",
          "title": "Nota de fundamentare",
          "type": "doc"
        }
      ]
    },
    {
      "currentUrl": "https://www.mdlpa.ro/pages/proiecthgaprobarebugetcni2023",
      "date": "07-02-2023",
      "name": "Proiect de HG pentru aprobarea bugetului de venituri şi cheltuieli pe anul 2023 al Societăţii Compania Naţională de Investiţii “C.N.I.”- SA aflată sub autoritatea Ministerului Dezvoltării, Lucrărilor Publice și Administraţiei",
      "documents": [
        {
          "date": "07-02-2023",
          "link": "https://www.mdlpa.ro/uploads/articole/attachments/63e20f1db434e072642912.doc",
          "title": "Proiect HG",
          "type": "doc"
        },
        {
          "date": "07-02-2023",
          "link": "https://www.mdlpa.ro/uploads/articole/attachments/63e20f1d75e61071542555.xls",
          "title": "Anexa",
          "type": "xls"
        },
        {
          "date": "07-02-2023",
          "link": "https://www.mdlpa.ro/uploads/articole/attachments/63e20f1d98ef0130617229.docx",
          "title": "Nota de fundamentare",
          "type": "doc"
        }
      ]
    },
    {
      "currentUrl": "https://www.mdlpa.ro/pages/proiecthgaprobarebugetanl03022023",
      "date": "03-02-2023",
      "name": "Proiect de HG pentru aprobarea bugetului de venituri şi cheltuieli pe anul 2023 al Agenţiei Naţionale pentru Locuinţe, instituţie publică aflată sub autoritatea Ministerului Dezvoltării, Lucrărilor Publice și Administraţiei",
      "documents": [
        {
          "date": "03-02-2023",
          "link": "https://www.mdlpa.ro/uploads/articole/attachments/63dcdb5c7916c542023475.docx",
          "title": "Proiect HG",
          "type": "doc"
        },
        {
          "date": "03-02-2023",
          "link": "https://www.mdlpa.ro/uploads/articole/attachments/63dcdb5c676b8228503351.ods",
          "title": "Anexa",
          "type": "xls"
        },
        {
          "date": "03-02-2023",
          "link": "https://www.mdlpa.ro/uploads/articole/attachments/63dcdb5c89a0a273585146.docx",
          "title": "Nota de fundamentare",
          "type": "doc"
        }
      ]
    },
    {
      "currentUrl": "https://www.mdlpa.ro/pages/proiectordinaprobarenormemetodologicegradincarcareconsortiuadministrativ",
      "date": "02-02-2023",
      "name": "Proiect de ORDIN pentru aprobarea Normelor metodologice cu privire la determinarea gradului de încărcare a personalului unităților administrativ-teritoriale, membre ale unui consorțiu administrativ",
      "documents": [
        {
          "date": "02-02-2023",
          "link": "https://www.mdlpa.ro/uploads/articole/attachments/63dbbf676b41f147259455.docx",
          "title": "Proiect Ordin",
          "type": "doc"
        },
        {
          "date": "02-02-2023",
          "link": "https://www.mdlpa.ro/uploads/articole/attachments/63dbbf6778f64151511954.docx",
          "title": "Anexa",
          "type": "doc"
        },
        {
          "date": "02-02-2023",
          "link": "https://www.mdlpa.ro/uploads/articole/attachments/63dbbf6787aa8520214164.docx",
          "title": "Referat de aprobare",
          "type": "doc"
        }
      ]
    },
    {
      "currentUrl": "https://www.mdlpa.ro/pages/proiecthgdesfiintareunitateasistentasanpetrubv",
      "date": "20-01-2023",
      "name": "Proiect de HG privind desființarea Unității de Asistență Medico-Psihosocială de Pneumoftiziologie Sânpetru, județul Brașov",
      "documents": [
        {
          "date": "20-01-2023",
          "link": "https://www.mdlpa.ro/uploads/articole/attachments/63ca848e694ca722148032.doc",
          "title": "Proiect HG",
          "type": "doc"
        },
        {
          "date": "20-01-2023",
          "link": "https://www.mdlpa.ro/uploads/articole/attachments/63ca8a73227b6435814263.docx",
          "title": "Nota de fundamentare",
          "type": "doc"
        }
      ]
    },
    {
      "currentUrl": "https://www.mdlpa.ro/pages/proiectordinaprobarenormemetodologiceaplicareoug182009",
      "date": "16-01-2023",
      "name": "Proiect de ORDIN pentru aprobarea normelor metodologice de aplicare a Ordonanței de urgență a Guvernului nr. 18/2009 privind creșterea performanței energetice a blocurilor de locuințe",
      "documents": [
        {
          "date": "16-01-2023",
          "link": "https://www.mdlpa.ro/uploads/articole/attachments/63c51e85e5eed788957515.doc",
          "title": "Ordin pentru aprobarea normelor metodologice de aplicare a Ordonanței de urgență a Guvernului nr. 18/2009 privind creșterea performanței energetice a blocurilor de locuințe",
          "type": "doc"
        },
        {
          "date": "16-01-2023",
          "link": "https://www.mdlpa.ro/uploads/articole/attachments/63c51e860b362982035605.docx",
          "title": "Referat de aprobare",
          "type": "doc"
        },
        {
          "date": "16-01-2023",
          "link": "https://www.mdlpa.ro/uploads/articole/attachments/63c51e79aa53e700857208.docx",
          "title": "Anexa A",
          "type": "doc"
        },
        {
          "date": "16-01-2023",
          "link": "https://www.mdlpa.ro/uploads/articole/attachments/63c51e838e678337067705.docx",
          "title": "Anexa 1",
          "type": "doc"
        },
        {
          "date": "16-01-2023",
          "link": "https://www.mdlpa.ro/uploads/articole/attachments/63c51e848bab6188979559.docx",
          "title": "Anexa 2",
          "type": "doc"
        },
        {
          "date": "16-01-2023",
          "link": "https://www.mdlpa.ro/uploads/articole/attachments/63c51e84c1960485556947.docx",
          "title": "Anexa 3",
          "type": "doc"
        },
        {
          "date": "16-01-2023",
          "link": "https://www.mdlpa.ro/uploads/articole/attachments/63c51e84d80bb596680208.docx",
          "title": "Anexa 4",
          "type": "doc"
        },
        {
          "date": "16-01-2023",
          "link": "https://www.mdlpa.ro/uploads/articole/attachments/63c51e850dbf9897116085.docx",
          "title": "Anexa 4 A",
          "type": "doc"
        },
        {
          "date": "16-01-2023",
          "link": "https://www.mdlpa.ro/uploads/articole/attachments/63c51e85194b5915036594.docx",
          "title": "Anexa 5",
          "type": "doc"
        },
        {
          "date": "16-01-2023",
          "link": "https://www.mdlpa.ro/uploads/articole/attachments/63c51e852afac499377544.xlsx",
          "title": "Anexa 5 A",
          "type": "xls"
        },
        {
          "date": "16-01-2023",
          "link": "https://www.mdlpa.ro/uploads/articole/attachments/63c51e859536a290183480.docx",
          "title": "Anexa 6",
          "type": "doc"
        },
        {
          "date": "16-01-2023",
          "link": "https://www.mdlpa.ro/uploads/articole/attachments/63c51e85c2086938808309.docx",
          "title": "Anexa 7",
          "type": "doc"
        }
      ]
    },
    {
      "currentUrl": "https://www.mdlpa.ro/pages/proiectdeougpentrumodificareasicompletareaoug472022privindajustareapreturilorcontractelordeachizitiepublica3012023",
      "date": "03-01-2023",
      "name": "Proiect de OG pentru modificarea și completarea Ordonanţei de urgenţă a Guvernului nr. 47/2022 privind ajustarea preţurilor contractelor de achiziţie publică/contractelor sectoriale/contractelor de concesiune/acordurilor-cadru și pentru stabilirea unor măsuri privind derularea programelor naționale de investiții",
      "documents": [
        {
          "date": "03-01-2023",
          "link": "https://www.mdlpa.ro/uploads/articole/attachments/63b443d912f26966711062.doc",
          "title": "Ordonanță a Guvernului pentru modificarea și completarea Ordonanţei de urgenţă a Guvernului nr. 47/2022 privind ajustarea preţurilor contractelor de achiziţie publică/contractelor sectoriale/contractelor de concesiune/acordurilor-cadru și pentru stabilirea unor măsuri privind derularea programelor naționale de investiții.",
          "type": "doc"
        },
        {
          "date": "03-01-2023",
          "link": "https://www.mdlpa.ro/uploads/articole/attachments/63b443d8d0b02167754861.docx",
          "title": "Notă de fundamentare",
          "type": "doc"
        }
      ]
    },
    {
      "currentUrl": "https://www.mdlpa.ro/pages/proiectdeougpentrumodificarealegii2122022privindmasuripentrureducerearisculuiseismic3012023",
      "date": "03-01-2023",
      "name": "Proiect de OG pentru modificarea Legii nr. 212/2022 privind măsuri pentru reducerea riscului seismic al clădirilor",
      "documents": [
        {
          "date": "03-01-2023",
          "link": "https://www.mdlpa.ro/uploads/articole/attachments/63b4422975011597418874.docx",
          "title": "Ordonanță a Guvernului pentru modificarea Legii nr. 212/2022 privind măsuri pentru reducerea riscului seismic al clădirilor",
          "type": "doc"
        },
        {
          "date": "03-01-2023",
          "link": "https://www.mdlpa.ro/uploads/articole/attachments/63b442295ea12650340078.docx",
          "title": "Notă de fundamentare",
          "type": "doc"
        }
      ]
    },
    {
      "currentUrl": "https://www.mdlpa.ro/pages/proiectdeougprivindstabilireadestinatieiunorsumerestituiteincontulfdi03012023",
      "date": "03-01-2023",
      "name": "Proiect de OG privind stabilirea destinației unor sume restituite în contul Fondului de Dezvoltare și Investiții",
      "documents": [
        {
          "date": "03-01-2023",
          "link": "https://www.mdlpa.ro/uploads/articole/attachments/63b4407407852970604046.docx",
          "title": "Ordonanță a Guvernului privind stabilirea destinației unor sume restituite în contul Fondului de Dezvoltare și Investiții",
          "type": "doc"
        },
        {
          "date": "03-01-2023",
          "link": "https://www.mdlpa.ro/uploads/articole/attachments/63b44073e4bef465133771.docx",
          "title": "Notă de fundamentare",
          "type": "doc"
        }
      ]
    },
    {
      "currentUrl": "https://www.mdlpa.ro/pages/proiectdeougprivindmodificareasicompletareaoug212010masuripentruintarireadisciplineiinconstructii03022023",
      "date": "03-01-2023",
      "name": "Proiect de OG pentru modificarea şi completarea Ordonanţei de urgenţă a Guvernului nr. 41/2010 privind unele măsuri pentru întărirea disciplinei în construcţii",
      "documents": [
        {
          "date": "03-01-2023",
          "link": "https://www.mdlpa.ro/uploads/articole/attachments/63b43eaac8921661309103.doc",
          "title": "Ordonanță a Guvernului pentru modificarea şi completarea Ordonanţei de urgenţă a Guvernului nr. 41/2010 privind unele măsuri pentru întărirea disciplinei în construcţii",
          "type": "doc"
        },
        {
          "date": "03-01-2023",
          "link": "https://www.mdlpa.ro/uploads/articole/attachments/63b43eaa2f91f634479090.docx",
          "title": "Notă de fundamentare",
          "type": "doc"
        }
      ]
    },
    {
      "currentUrl": "https://www.mdlpa.ro/pages/hgpentrumodificareasicompletareahg4772020privindorganizareasifunctionareamdlpa20122022",
      "date": "29-12-2022",
      "name": "Proiect de HG pentru modificarea și completarea Hotărârii Guvernului nr. 477/2020 privind organizarea și funcționarea Ministerului Dezvoltării, Lucrărilor Publice și Administrației",
      "documents": [
        {
          "date": "29-12-2022",
          "link": "https://www.mdlpa.ro/uploads/articole/attachments/63ad682aa1eac782280462.docx",
          "title": "Hotărâre a Guvernului pentru modificarea și completarea Hotărârii Guvernului nr. 477/2020 privind organizarea și funcționarea Ministerului Dezvoltării, Lucrărilor Publice și Administrației",
          "type": "doc"
        },
        {
          "date": "29-12-2022",
          "link": "https://www.mdlpa.ro/uploads/articole/attachments/63ad682a93336029346011.docx",
          "title": "Notă de fundamentare",
          "type": "doc"
        },
        {
          "date": "29-12-2022",
          "link": "https://www.mdlpa.ro/uploads/articole/attachments/63ad682a7eea1261997236.xlsx",
          "title": "Anexa 1 - Organigrama MDLPA",
          "type": "xls"
        }
      ]
    },
    {
      "currentUrl": "https://www.mdlpa.ro/pages/proiectordinaprobarereglementareghidindicativrtc7",
      "date": "23-12-2022",
      "name": "Proiect de ORDIN pentru aprobarea reglementării tehnice „Ghid privind metodele de prevenire și control a pătrunderii radonului în clădirile noi, indicativ RTC 7”",
      "documents": [
        {
          "date": "23-12-2022",
          "link": "https://www.mdlpa.ro/uploads/articole/attachments/63a593792c5f1548720127.doc",
          "title": "Ordin pentru aprobarea reglementării tehnice „Ghid privind metodele de prevenire și control a pătrunderii radonului în clădirile noi, indicativ RTC 7”",
          "type": "doc"
        },
        {
          "date": "23-12-2022",
          "link": "https://www.mdlpa.ro/uploads/articole/attachments/63a593793eb27001364192.doc",
          "title": "Referat de aprobare",
          "type": "doc"
        },
        {
          "date": "23-12-2022",
          "link": "https://www.mdlpa.ro/uploads/articole/attachments/63a59379a2b9a140332537.docx",
          "title": "Anexa",
          "type": "doc"
        }
      ]
    },
    {
      "currentUrl": "https://www.mdlpa.ro/pages/proiectordinaprobarereglementaritehniceghidcladirireducerenivelradonindicativrtc6",
      "date": "23-12-2022",
      "name": "Proiect de ORDIN pentru aprobarea reglementării tehnice „Ghid privind metodele de remediere în clădiri existente pentru reducerea nivelului de expunere la radon, indicativ RTC 6”",
      "documents": [
        {
          "date": "23-12-2022",
          "link": "https://www.mdlpa.ro/uploads/articole/attachments/63a591f8bf576203923162.doc",
          "title": "Ordin pentru aprobarea reglementării tehnice „Ghid privind metodele de remediere în clădiri existente pentru reducerea nivelului de expunere la radon, indicativ RTC 6”",
          "type": "doc"
        },
        {
          "date": "23-12-2022",
          "link": "https://www.mdlpa.ro/uploads/articole/attachments/63a591f8d1f8a065892282.doc",
          "title": "Referat de aprobare",
          "type": "doc"
        }
      ]
    },
    {
      "currentUrl": "https://www.mdlpa.ro/pages/proiecthgaprobareabuget2022anl",
      "date": "15-12-2022",
      "name": "Proiect de HG pentru aprobarea bugetului rectificat de venituri şi cheltuieli pe anul 2022 al Agenţiei Naţionale pentru Locuinţe, instituţie publică aflată sub autoritatea Ministerului Dezvoltării, Lucrărilor Publice și Administraţiei",
      "documents": [
        {
          "date": "15-12-2022",
          "link": "https://www.mdlpa.ro/uploads/articole/attachments/639acb1941e1d145145886.docx",
          "title": "Hotărâre a Guvernului pentru aprobarea bugetului rectificat de venituri şi cheltuieli pe anul 2022 al Agenţiei Naţionale pentru Locuinţe, instituţie publică aflată sub autoritatea Ministerului Dezvoltării, Lucrărilor Publice și Administraţiei",
          "type": "doc"
        },
        {
          "date": "15-12-2022",
          "link": "https://www.mdlpa.ro/uploads/articole/attachments/639acb1952fc9047197953.docx",
          "title": "Nota de fundamentare",
          "type": "doc"
        },
        {
          "date": "15-12-2022",
          "link": "https://www.mdlpa.ro/uploads/articole/attachments/639acb192347f967461077.ods",
          "title": "Anexa",
          "type": "xls"
        }
      ]
    },
    {
      "currentUrl": "https://www.mdlpa.ro/pages/proiecthgaprobabugetcni2022",
      "date": "12-12-2022",
      "name": "Proiect de HG pentru aprobarea bugetului rectificat de venituri şi cheltuieli pe anul 2022 al Societăţii Compania Naţională de Investiţii “C.N.I.”- SA aflată sub autoritatea Ministerului Dezvoltării, Lucrărilor Publice  și Administraţiei",
      "documents": [
        {
          "date": "12-12-2022",
          "link": "https://www.mdlpa.ro/uploads/articole/attachments/63982bdf7f25f400120802.doc",
          "title": "Hotărâre a Guvernului pentru aprobarea bugetului rectificat de venituri şi cheltuieli pe anul 2022 al Societăţii Compania Naţională de Investiţii “C.N.I.”- SA aflată sub autoritatea Ministerului Dezvoltării, Lucrărilor Publice  și Administraţiei",
          "type": "doc"
        },
        {
          "date": "12-12-2022",
          "link": "https://www.mdlpa.ro/uploads/articole/attachments/63982bdf62366717080728.docx",
          "title": "Nota de fundamentare",
          "type": "doc"
        },
        {
          "date": "12-12-2022",
          "link": "https://www.mdlpa.ro/uploads/articole/attachments/63982bdf15704144711923.xls",
          "title": "Anexa",
          "type": "xls"
        }
      ]
    },
    {
      "currentUrl": "https://www.mdlpa.ro/pages/proiectlegeinfiintarefundaturavrancea07122022",
      "date": "07-12-2022",
      "name": "Proiect de LEGE pentru înființarea satului Fundătura, judeţul Vrancea, prin reorganizarea comunei Păulești, judeţul Vrancea",
      "documents": [
        {
          "date": "07-12-2022",
          "link": "https://www.mdlpa.ro/uploads/articole/attachments/6390602fa470e488107494.docx",
          "title": "Proiect de Lege pentru înființarea satului Fundătura, judeţul Vrancea, prin reorganizarea comunei Păulești, judeţul Vrancea",
          "type": "doc"
        },
        {
          "date": "07-12-2022",
          "link": "https://www.mdlpa.ro/uploads/articole/attachments/6390602f8f113132083110.docx",
          "title": "Expunere de motive",
          "type": "doc"
        }
      ]
    },
    {
      "currentUrl": "https://www.mdlpa.ro/pages/proiecthgmodifcareanexaog1422008aprobareplanamenajareteuritoriunationalzoneturistice",
      "date": "29-11-2022",
      "name": "Proiect de HG pentru modificarea Anexelor la Ordonanţa de urgenţă a Guvernului nr. 142/2008 privind aprobarea Planului de amenajare a teritoriului naţional Secţiunea a VIII-a - zone cu resurse turistice",
      "documents": [
        {
          "date": "29-11-2022",
          "link": "https://www.mdlpa.ro/uploads/articole/attachments/6385f74c8d54c959985337.docx",
          "title": "Hotărâre a Guvernului pentru modificarea Anexelor la Ordonanţa de urgenţă a Guvernului nr. 142/2008 privind aprobarea Planului de amenajare a teritoriului naţional Secţiunea a VIII-a - zone cu resurse turistice",
          "type": "doc"
        },
        {
          "date": "29-11-2022",
          "link": "https://www.mdlpa.ro/uploads/articole/attachments/6385f74ca49b6479020334.doc",
          "title": "Nota de fundamentare",
          "type": "doc"
        },
        {
          "date": "29-11-2022",
          "link": "https://www.mdlpa.ro/uploads/articole/attachments/6385f74a63e01775855700.doc",
          "title": "Anexa 1",
          "type": "doc"
        },
        {
          "date": "29-11-2022",
          "link": "https://www.mdlpa.ro/uploads/articole/attachments/6385f74af2f63305459370.docx",
          "title": "Anexa 2",
          "type": "doc"
        },
        {
          "date": "29-11-2022",
          "link": "https://www.mdlpa.ro/uploads/articole/attachments/6385f74b2a985892719877.doc",
          "title": "Anexa 3",
          "type": "doc"
        },
        {
          "date": "29-11-2022",
          "link": "https://www.mdlpa.ro/uploads/articole/attachments/6385f74b7e137039055560.docx",
          "title": "Anexa 4",
          "type": "doc"
        },
        {
          "date": "29-11-2022",
          "link": "https://www.mdlpa.ro/uploads/articole/attachments/6385f74b9c39c961783962.doc",
          "title": "Anexa 5",
          "type": "doc"
        },
        {
          "date": "29-11-2022",
          "link": "https://www.mdlpa.ro/uploads/articole/attachments/6385f74bdfd7c223456533.docx",
          "title": "Anexa 6",
          "type": "doc"
        },
        {
          "date": "29-11-2022",
          "link": "https://www.mdlpa.ro/uploads/articole/attachments/6385f74c105e1398331503.doc",
          "title": "Anexa 7",
          "type": "doc"
        },
        {
          "date": "29-11-2022",
          "link": "https://www.mdlpa.ro/uploads/articole/attachments/6385f74c75424408211111.docx",
          "title": "Anexa 8",
          "type": "doc"
        }
      ]
    },
    {
      "currentUrl": "https://www.mdlpa.ro/pages/proiecthgmodifcarehg8962003aprobarenormeaplicarelegea152003construirelocuinte",
      "date": "29-11-2022",
      "name": "Proiect de HG pentru modificarea Hotărârii nr. 896 din 29 iulie 2003 pentru aprobarea Normelor metodologice de aplicare a Legii nr. 15/2003 privind sprijinul acordat tinerilor pentru construirea unei locuinţe proprietate personală",
      "documents": [
        {
          "date": "29-11-2022",
          "link": "https://www.mdlpa.ro/uploads/articole/attachments/6385d803b2cdb394530320.doc",
          "title": "Hotărâre a Guvernului pentru modificarea Hotărârii nr. 896 din 29 iulie 2003 pentru aprobarea Normelor metodologice de aplicare a Legii nr. 15/2003 privind sprijinul acordat tinerilor pentru construirea unei locuinţe proprietate personală",
          "type": "doc"
        },
        {
          "date": "29-11-2022",
          "link": "https://www.mdlpa.ro/uploads/articole/attachments/6385d8037eff8817547135.doc",
          "title": "Nota de fundamentare",
          "type": "doc"
        }
      ]
    },
    {
      "currentUrl": "https://www.mdlpa.ro/pages/proiectordinaprobarereglementaritehnicenormativsecuritateincendiuindicativp11812022",
      "date": "25-11-2022",
      "name": "Proiect de ORDIN pentru aprobarea reglementării tehnice „Normativ privind securitatea la incendiu a construcțiilor, indicativ P 118/1-2022”",
      "documents": [
        {
          "date": "25-11-2022",
          "link": "https://www.mdlpa.ro/uploads/articole/attachments/63806f3d6905a446607221.doc",
          "title": "Ordin pentru aprobarea reglementării tehnice „Normativ privind securitatea la incendiu a construcțiilor, indicativ P 118/1-2022”",
          "type": "doc"
        },
        {
          "date": "25-11-2022",
          "link": "https://www.mdlpa.ro/uploads/articole/attachments/63806f3f7a628070954810.doc",
          "title": "Referat de aprobare",
          "type": "doc"
        },
        {
          "date": "25-11-2022",
          "link": "https://www.mdlpa.ro/uploads/articole/attachments/63806f3f63232813566666.docx",
          "title": "Anexa",
          "type": "doc"
        }
      ]
    },
    {
      "currentUrl": "https://www.mdlpa.ro/pages/proiectougmodificarecompletareoug572019codadministrativ23112022",
      "date": "23-11-2022",
      "name": "Proiect de OUG pentru modificarea și completarea Ordonanței de urgență a Guvernului nr. 57/2019 privind Codul administrativ",
      "documents": [
        {
          "date": "23-11-2022",
          "link": "https://www.mdlpa.ro/uploads/articole/attachments/637dfd917e903094510405.docx",
          "title": "Ordonanță de urgență a Guvernului pentru modificarea și completarea Ordonanței de urgență a Guvernului nr. 57/2019 privind Codul administrativ",
          "type": "doc"
        },
        {
          "date": "23-11-2022",
          "link": "https://www.mdlpa.ro/uploads/articole/attachments/637dfd913cb14520406893.doc",
          "title": "Nota de fundamentare",
          "type": "doc"
        },
        {
          "date": "23-11-2022",
          "link": "https://www.mdlpa.ro/uploads/articole/attachments/637dfd90911b8929589729.docx",
          "title": "Anexa 1",
          "type": "doc"
        },
        {
          "date": "23-11-2022",
          "link": "https://www.mdlpa.ro/uploads/articole/attachments/637dfd90187ae938934672.docx",
          "title": "Anexa 2",
          "type": "doc"
        }
      ]
    },
    {
      "currentUrl": "https://www.mdlpa.ro/pages/ordinmodificarecompletareschemaomdrap112110752014",
      "date": "23-11-2022",
      "name": "Proiect de ORDIN pentru modificarea și completarea anexei la Ordinul viceprim-ministrului, ministrul dezvoltării regionale şi administraţiei publice şi al ministrului delegat pentru buget nr. 1.121/1.075/2014 privind aprobarea Schemei de ajutor de stat acordat în perioada 2014 – 30 iunie 2023 operatorilor economici care prestează serviciul de interes economic general de producere, transport, distribuție și furnizare a energiei termice în sistem centralizat către populație",
      "documents": [
        {
          "date": "23-11-2022",
          "link": "https://www.mdlpa.ro/uploads/articole/attachments/637de52660519835273873.docx",
          "title": "Ordin pentru modificarea și completarea anexei la Ordinul viceprim-ministrului, ministrul dezvoltării regionale şi administraţiei publice şi al ministrului delegat pentru buget nr. 1.121/1.075/2014 privind aprobarea Schemei de ajutor de stat acordat în perioada 2014 – 30 iunie 2023 operatorilor economici care prestează serviciul de interes economic general de producere, transport, distribuție și furnizare a energiei termice în sistem centralizat către populație",
          "type": "doc"
        },
        {
          "date": "23-11-2022",
          "link": "https://www.mdlpa.ro/uploads/articole/attachments/637de50c57a02840696233.docx",
          "title": "Referat de aprobare",
          "type": "doc"
        }
      ]
    },
    {
      "currentUrl": "https://www.mdlpa.ro/pages/proiectordinaprobareschemafinantarepnrrc11",
      "date": "17-11-2022",
      "name": "Proiect de ORDIN pentru aprobarea Schemei de finanțare - Condiții de accesare a fondurilor europene aferente Planului Național de Redresare și Reziliență în cadrul apelului în cadrul apelului de proiecte PNRR/2022/C11/I4, Componenta 11 – Turism și cultură, Investiția I.4 – Implementarea a 3.000 km trasee cicloturistice",
      "documents": [
        {
          "date": "17-11-2022",
          "link": "https://www.mdlpa.ro/uploads/articole/attachments/6376587a31cbb250197462.docx",
          "title": "Ordin pentru aprobarea Schemei de finanțare - Condiții de accesare a fondurilor europene aferente Planului Național de Redresare și Reziliență în cadrul apelului de proiecte PNRR/2022/C11/I4, Componenta 11 – Turism și cultură, Investiția I.4 – Implementarea a 3.000 km trasee cicloturistice",
          "type": "doc"
        },
        {
          "date": "17-11-2022",
          "link": "https://www.mdlpa.ro/uploads/articole/attachments/6376587a40c73628561638.docx",
          "title": "Referat de aprobare",
          "type": "doc"
        },
        {
          "date": "17-11-2022",
          "link": "https://www.mdlpa.ro/uploads/articole/attachments/6376587a97149736255958.docx",
          "title": "Anexa",
          "type": "doc"
        }
      ]
    },
    {
      "currentUrl": "https://www.mdlpa.ro/pages/proiecthgmodificarecompletarenormeaplicarelegea1521998anlhg9622001",
      "date": "11-11-2022",
      "name": "Proiect de HG privind modificarea și completarea Normelor metodologice pentru punerea în aplicare a prevederilor Legii nr. 152/1998 privind înfiinţarea Agenţiei Naţionale pentru Locuinţe, aprobate prin Hotărârea Guvernului nr. 962/2001",
      "documents": [
        {
          "date": "11-11-2022",
          "link": "https://www.mdlpa.ro/uploads/articole/attachments/636e30e476c01690846393.doc",
          "title": "Hotărâre a Guvernului privind modificarea și completarea Normelor metodologice pentru punerea în aplicare a prevederilor Legii nr. 152/1998 privind înfiinţarea Agenţiei Naţionale pentru Locuinţe, aprobate prin Hotărârea Guvernului nr. 962/2001",
          "type": "doc"
        },
        {
          "date": "11-11-2022",
          "link": "https://www.mdlpa.ro/uploads/articole/attachments/636e30e4916e6754582829.doc",
          "title": "Nota de fundamentare",
          "type": "doc"
        },
        {
          "date": "11-11-2022",
          "link": "https://www.mdlpa.ro/uploads/articole/attachments/636e30e4a6ae0445963285.doc",
          "title": "Anexa 1",
          "type": "doc"
        },
        {
          "date": "11-11-2022",
          "link": "https://www.mdlpa.ro/uploads/articole/attachments/636e30e4be4fb866274843.doc",
          "title": "Anexa 2",
          "type": "doc"
        },
        {
          "date": "11-11-2022",
          "link": "https://www.mdlpa.ro/uploads/articole/attachments/636e30e4e34bd730299265.doc",
          "title": "Anexa 3",
          "type": "doc"
        },
        {
          "date": "11-11-2022",
          "link": "https://www.mdlpa.ro/uploads/articole/attachments/636e30e50ff75850157770.doc",
          "title": "Tabel comparativ",
          "type": "doc"
        }
      ]
    },
    {
      "currentUrl": "https://www.mdlpa.ro/pages/proiecthgaprobarestrategiefunctiepublica20222027",
      "date": "10-11-2022",
      "name": "Proiect de HG pentru aprobarea Strategiei în domeniul funcției publice pentru perioada 2022-2027",
      "documents": [
        {
          "date": "10-11-2022",
          "link": "https://www.mdlpa.ro/uploads/articole/attachments/636cdd5db2e1a785982780.doc",
          "title": "Hotărâre a Guvernului pentru aprobarea Strategiei în domeniul funcției publice pentru perioada 2022-2027",
          "type": "doc"
        },
        {
          "date": "10-11-2022",
          "link": "https://www.mdlpa.ro/uploads/articole/attachments/636cdd5e0ac18357361309.doc",
          "title": "Nota de fundamentare",
          "type": "doc"
        },
        {
          "date": "10-11-2022",
          "link": "https://www.mdlpa.ro/uploads/articole/attachments/636cdd5d91d64131462625.docx",
          "title": "Anexa",
          "type": "doc"
        }
      ]
    },
    {
      "currentUrl": "https://www.mdlpa.ro/pages/proiecthgaprobaredocumentatieurbanismactualizareplanurbanisticmures",
      "date": "10-11-2022",
      "name": "Proiect de HG pentru aprobarea documentației de urbanism „Actualizare Plan Urbanistic General și regulament Local de Urbanism comuna Saschiz, județul Mureș”",
      "documents": [
        {
          "date": "10-11-2022",
          "link": "https://www.mdlpa.ro/uploads/articole/attachments/636cb31aab75e178846590.doc",
          "title": "Hotărâre a Guvernului pentru aprobarea documentației de urbanism „Actualizare Plan Urbanistic General și regulament Local de Urbanism comuna Saschiz, județul Mureș”",
          "type": "doc"
        },
        {
          "date": "10-11-2022",
          "link": "https://www.mdlpa.ro/uploads/articole/attachments/636cb31a5b383172605976.docx",
          "title": "Nota de fundamentare",
          "type": "doc"
        }
      ]
    },
    {
      "currentUrl": "https://www.mdlpa.ro/pages/proiectougcompletareanexa5oug572019codadministrativ",
      "date": "10-11-2022",
      "name": "Proiect de OUG pentru completarea Anexei nr. 5¹ la Ordonanţa de urgenţă a Guvernului nr. 57/2019 privind Codul administrativ",
      "documents": [
        {
          "date": "10-11-2022",
          "link": "https://www.mdlpa.ro/uploads/articole/attachments/636cb177e8ba4669425386.docx",
          "title": "Ordonanță de urgență a Guvernului pentru completarea Anexei nr. 5¹ la Ordonanţa de urgenţă a Guvernului nr. 57/2019 privind Codul administrativ",
          "type": "doc"
        },
        {
          "date": "10-11-2022",
          "link": "https://www.mdlpa.ro/uploads/articole/attachments/636cb177d4da3519815186.docx",
          "title": "Nota de fundamentare",
          "type": "doc"
        }
      ]
    },
    {
      "currentUrl": "https://www.mdlpa.ro/pages/proiectordincompletarenormeaplicarelegea3502001amenajareteritoriuurbanism",
      "date": "04-11-2022",
      "name": "Proiect de ORDIN privind completarea Normelor metodologice de aplicare a Legii nr. 350/2001 privind amenajarea teritoriului și urbanismul și de elaborare și actualizare a documentațiilor de urbanism, aprobate prin Ordinul viceprim-ministrului, ministrul dezvoltării regionale și administrației publice nr. 233/2016",
      "documents": [
        {
          "date": "04-11-2022",
          "link": "https://www.mdlpa.ro/uploads/articole/attachments/6364c3f967e7d678881476.docx",
          "title": "Ordin privind completarea Normelor metodologice de aplicare a Legii nr. 350/2001 privind amenajarea teritoriului și urbanismul și de elaborare și actualizare a documentațiilor de urbanism, aprobate prin Ordinul viceprim-ministrului, ministrul dezvoltării regionale și administrației publice nr. 233/2016",
          "type": "doc"
        },
        {
          "date": "04-11-2022",
          "link": "https://www.mdlpa.ro/uploads/articole/attachments/6364c3f97b96e205958972.docx",
          "title": "Referat de aprobare",
          "type": "doc"
        }
      ]
    },
    {
      "currentUrl": "https://www.mdlpa.ro/pages/proiecthgrecunoastereasociatiaadrroregutilitatepublica",
      "date": "02-11-2022",
      "name": "Proiect de HG privind recunoaşterea Asociației Agențiilor pentru Dezvoltare Regională din România ROREG ca fiind de utilitate publică",
      "documents": [
        {
          "date": "02-11-2022",
          "link": "https://www.mdlpa.ro/uploads/articole/attachments/636282ae38975018099651.doc",
          "title": "Hotărâre a Guvernului privind recunoaşterea Asociației Agențiilor pentru Dezvoltare Regională din România ROREG ca fiind de utilitate publică",
          "type": "doc"
        },
        {
          "date": "02-11-2022",
          "link": "https://www.mdlpa.ro/uploads/articole/attachments/636282ae1ffae510860977.DOC",
          "title": "Nota de fundamentare",
          "type": "doc"
        }
      ]
    },
    {
      "currentUrl": "https://www.mdlpa.ro/pages/proiectougstabiliremasuriindeplinieretintepnrrc10c11c14c15",
      "date": "21-10-2022",
      "name": "Proiect de OUG privind stabilirea unor măsuri necesare pentru îndeplinirea jaloanelor și țintelor din Planul Național de Redresare și Reziliență aferente Componentei 10 - Fondul local, Componentei 11- Turism și Cultură, Componentei 14 – Buna guvernanță și Componentei 15 – Educație, precum și pentru completarea Legii nr. 50/1991 privind autorizarea executării lucrărilor de construcţii",
      "documents": [
        {
          "date": "21-10-2022",
          "link": "https://www.mdlpa.ro/uploads/articole/attachments/63524a2127c88826060818.docx",
          "title": "Ordonanță de urgență a Guvernului privind stabilirea unor măsuri necesare pentru îndeplinirea jaloanelor și țintelor din Planul Național de Redresare și Reziliență aferente Componentei 10 - Fondul local, Componentei 11- Turism și Cultură, Componentei 14 – Buna guvernanță și Componentei 15 – Educație, precum și pentru completarea Legii nr. 50/1991 privind autorizarea executării lucrărilor de construcţii",
          "type": "doc"
        },
        {
          "date": "21-10-2022",
          "link": "https://www.mdlpa.ro/uploads/articole/attachments/63524a2113715127450129.docx",
          "title": "Nota de fundamentare",
          "type": "doc"
        }
      ]
    },
    {
      "currentUrl": "https://www.mdlpa.ro/pages/proiectougcompletareog362006masurisistemecentralizatealimentareenergietermica",
      "date": "20-10-2022",
      "name": "Proiect de OUG pentru completarea Ordonanței Guvernului nr. 36/2006 privind unele măsuri pentru funcționarea sistemelor centralizate de alimentare cu energie termică a populației",
      "documents": [
        {
          "date": "20-10-2022",
          "link": "https://www.mdlpa.ro/uploads/articole/attachments/6351092e8ff28719401740.docx",
          "title": "Ordonanță de urgență a Guvernului pentru completarea Ordonanței Guvernului nr. 36/2006 privind unele măsuri pentru funcționarea sistemelor centralizate de alimentare cu energie termică a populației",
          "type": "doc"
        },
        {
          "date": "20-10-2022",
          "link": "https://www.mdlpa.ro/uploads/articole/attachments/6351092e7c262989009702.docx",
          "title": "Nota de fundamentare",
          "type": "doc"
        }
      ]
    },
    {
      "currentUrl": "https://www.mdlpa.ro/pages/proiectdeordinaprobareanormelormetaplicl2122022privindrrseismicprivindderulareaprogrnatdeconsacladirilorcuriscseismic",
      "date": "14-10-2022",
      "name": "Proiect de ORDIN pentru aprobarea Normelor metodologice de aplicare a prevederilor Legii nr. 212/2022 privind unele măsuri pentru reducerea riscului seismic al clădirilor, privind derularea Programului național de consolidare a clădirilor cu risc seismic ridicat",
      "documents": [
        {
          "date": "14-10-2022",
          "link": "https://www.mdlpa.ro/uploads/articole/attachments/6349451bdca69171227379.doc",
          "title": "Ordin pentru aprobarea Normelor metodologice de aplicare a prevederilor Legii nr. 212/2022 privind unele măsuri pentru reducerea riscului seismic al clădirilor, privind derularea Programului național de consolidare a clădirilor cu risc seismic ridicat",
          "type": "doc"
        },
        {
          "date": "14-10-2022",
          "link": "https://www.mdlpa.ro/uploads/articole/attachments/6349451bea9b9668522486.docx",
          "title": "Referat de aprobare",
          "type": "doc"
        },
        {
          "date": "14-10-2022",
          "link": "https://www.mdlpa.ro/uploads/articole/attachments/6349451bd0c96079346653.doc",
          "title": "Norme metodologice",
          "type": "doc"
        },
        {
          "date": "14-10-2022",
          "link": "https://www.mdlpa.ro/uploads/articole/attachments/6349451b5f3b8496526600.docx",
          "title": "Anexa 1A (solicitare de includere in program - clădiri rezidențiale)",
          "type": "doc"
        },
        {
          "date": "14-10-2022",
          "link": "https://www.mdlpa.ro/uploads/articole/attachments/6349451b6d315349665282.docx",
          "title": "Anexa 1B (solicitare includere în program - clădiri de interes și utilitate publică",
          "type": "doc"
        },
        {
          "date": "14-10-2022",
          "link": "https://www.mdlpa.ro/uploads/articole/attachments/6349451b7b224653423169.xlsx",
          "title": "Anexa 2 (deviz general cu formule)",
          "type": "xls"
        },
        {
          "date": "14-10-2022",
          "link": "https://www.mdlpa.ro/uploads/articole/attachments/6349451b3879e739685116.xls",
          "title": "Anexa 3 (solicitare de transfer)",
          "type": "xls"
        },
        {
          "date": "14-10-2022",
          "link": "https://www.mdlpa.ro/uploads/articole/attachments/6349451b89093720872065.docx",
          "title": "Anexa 4 (aviz MDLPA)",
          "type": "doc"
        },
        {
          "date": "14-10-2022",
          "link": "https://www.mdlpa.ro/uploads/articole/attachments/6349451b47f44817891648.xls",
          "title": "Anexa 5 (justificare utilizare sume)",
          "type": "xls"
        },
        {
          "date": "14-10-2022",
          "link": "https://www.mdlpa.ro/uploads/articole/attachments/6349451b955fb084914398.docx",
          "title": "Anexa 6A (raport finalizare obiectiv)",
          "type": "doc"
        },
        {
          "date": "14-10-2022",
          "link": "https://www.mdlpa.ro/uploads/articole/attachments/6349451ba07da479646998.docx",
          "title": "Anexa 6B (raport finalizare obiectiv)",
          "type": "doc"
        },
        {
          "date": "14-10-2022",
          "link": "https://www.mdlpa.ro/uploads/articole/attachments/6349451bb0512134386990.doc",
          "title": "Anexa 7 (lista de lucrări eligibile și indicatori de performanță - clădiri rezidențiale)",
          "type": "doc"
        },
        {
          "date": "14-10-2022",
          "link": "https://www.mdlpa.ro/uploads/articole/attachments/6349451bbf5a4082453739.doc",
          "title": "Anexa 8 (lista de lucrări eligibile și indicatori de performanță - clădiri publice)",
          "type": "doc"
        }
      ]
    },
    {
      "currentUrl": "https://www.mdlpa.ro/pages/proiectordinaprobarereglementaretehnicartc10",
      "date": "13-10-2022",
      "name": "Proiect de ORDIN pentru aprobarea reglementării tehnice „Metodologie de evaluare vizuală rapidă a clădirilor, indicativ RTC-10”",
      "documents": [
        {
          "date": "13-10-2022",
          "link": "https://www.mdlpa.ro/uploads/articole/attachments/63480fcb1be68062399876.doc",
          "title": "Ordin pentru aprobarea reglementării tehnice „Metodologie de evaluare vizuală rapidă a clădirilor, indicativ RTC-10”",
          "type": "doc"
        },
        {
          "date": "13-10-2022",
          "link": "https://www.mdlpa.ro/uploads/articole/attachments/63480fcb2e92d119578551.doc",
          "title": "Referat de aprobare",
          "type": "doc"
        },
        {
          "date": "13-10-2022",
          "link": "https://www.mdlpa.ro/uploads/articole/attachments/63480fcb015cb787989953.docx",
          "title": "Anexa",
          "type": "doc"
        }
      ]
    },
    {
      "currentUrl": "https://www.mdlpa.ro/pages/proiectordinmodificarenormeoug952021pnianghelsaligny",
      "date": "30-09-2022",
      "name": "Proiect de ORDIN pentru modificarea și completarea Normelor metodologice pentru punerea în aplicare a prevederilor Ordonanţei de urgenţă a Guvernului nr. 95/2021 pentru aprobarea Programului Național de Investiţii \"Anghel Saligny\", pentru categoriile de investiții prevăzute la art. 4 alin. (1) lit. a) – d) din Ordonanţa de urgenţă a Guvernului nr. 95/2021, aprobate prin Ordinul ministrului dezvoltării, lucrărilor publice și administrației nr. 1333/2021",
      "documents": [
        {
          "date": "30-09-2022",
          "link": "https://www.mdlpa.ro/uploads/articole/attachments/6336cd5aee9b9001784920.doc",
          "title": "Ordin pentru modificarea și completarea Normelor metodologice pentru punerea în aplicare a prevederilor Ordonanţei de urgenţă a Guvernului nr. 95/2021 pentru aprobarea Programului Național de Investiţii \"Anghel Saligny\", pentru categoriile de investiții prevăzute la art. 4 alin. (1) lit. a) – d) din Ordonanţa de urgenţă a Guvernului nr. 95/2021, aprobate prin Ordinul ministrului dezvoltării, lucrărilor publice și administrației nr. 1333/2021",
          "type": "doc"
        },
        {
          "date": "30-09-2022",
          "link": "https://www.mdlpa.ro/uploads/articole/attachments/6336cd5b0702b078539382.docx",
          "title": "Referat de aprobare",
          "type": "doc"
        },
        {
          "date": "30-09-2022",
          "link": "https://www.mdlpa.ro/uploads/articole/attachments/6336cd5adf018754390865.xlsx",
          "title": "Anexa",
          "type": "xls"
        }
      ]
    },
    {
      "currentUrl": "https://www.mdlpa.ro/pages/proiecthgaprobarebugetvenituricheltuieli2022cni",
      "date": "30-09-2022",
      "name": "Proiect de HG pentru aprobarea bugetului rectificat de venituri și cheltuieli pe anul 2022 al al Societăţii Compania Naţională de Investiţii “C.N.I.”- SA, aflată sub autoritatea Ministerului Dezvoltării, Lucrărilor Publice  și Administraţiei",
      "documents": [
        {
          "date": "30-09-2022",
          "link": "https://www.mdlpa.ro/uploads/articole/attachments/6336c9b99850e895523590.doc",
          "title": "Hotărâre a Guvernului pentru aprobarea bugetului rectificat de venituri și cheltuieli pe anul 2022 al al Societăţii Compania Naţională de Investiţii “C.N.I.”- SA, aflată sub autoritatea Ministerului Dezvoltării, Lucrărilor Publice  și Administraţiei",
          "type": "doc"
        },
        {
          "date": "30-09-2022",
          "link": "https://www.mdlpa.ro/uploads/articole/attachments/6336c9b98719c470580469.docx",
          "title": "Nota de fundamentare",
          "type": "doc"
        },
        {
          "date": "30-09-2022",
          "link": "https://www.mdlpa.ro/uploads/articole/attachments/6336c9b97813b354170302.xls",
          "title": "Anexa",
          "type": "xls"
        }
      ]
    },
    {
      "currentUrl": "https://www.mdlpa.ro/pages/proiectordinmodificarecompletareghidconditiiaccesarefonduripnrr",
      "date": "20-09-2022",
      "name": "Proiect de ORDIN pentru modificarea și completarea Ghidului Specific – Condiții de accesare a fondurilor europene aferente PNRR, în cadrul apelurilor de proiecte PNRR/2022/C10, Componenta 10-Fondul local, aprobat prin ordinul ministrului dezvoltării, lucrărilor publice și administrației nr. 999/2022",
      "documents": [
        {
          "date": "20-09-2022",
          "link": "https://www.mdlpa.ro/uploads/articole/attachments/6329c7491732d635448507.docx",
          "title": "Ordin pentru modificarea și completarea Ghidului Specific – Condiții de accesare a fondurilor europene aferente PNRR, în cadrul apelurilor de proiecte PNRR/2022/C10, Componenta 10-Fondul local, aprobat prin ordinul ministrului dezvoltării, lucrărilor publice și administrației nr. 999/2022",
          "type": "doc"
        },
        {
          "date": "20-09-2022",
          "link": "https://www.mdlpa.ro/uploads/articole/attachments/6329c7492b3c7461160216.docx",
          "title": "Referat de aprobare",
          "type": "doc"
        }
      ]
    },
    {
      "currentUrl": "https://www.mdlpa.ro/pages/proiectordinmodificareghiduripnrr",
      "date": "20-09-2022",
      "name": "Proiect de ORDIN pentru modificarea și completarea Ghidurilor Specifice – Condiții de accesare a fondurilor europene aferente PNRR, Axa 1 – Schema de granturi pentru eficiență energetică și reziliență în clădiri rezidențiale multifamiliale (Operațiunea A.1 – Renovarea integrată (consolidare seismică și renovarea energetică moderată) a clădirilor rezidențiale multifamiliale; Operațiunea A.2 –  Renovarea energetică moderată a clădirilor rezidențiale multifamiliale pentru comunități expuse riscului de sărăcie și excluziune socială; Operațiunea A.3 - Renovarea energetică moderată sau aprofundată a clădirilor rezidențiale multifamiliale) și Axa 2 – Schema de granturi pentru eficiență energetică și reziliență în clădiri publice (Operațiunea B.1 - Renovarea integrată (consolidare seismică și renovare energetică moderată) a clădirilor publice și Operațiunea B.2 – Renovarea energetică moderată sau aprofundată a clădirilor), aprobate prin ordinele ministrului dezvoltării, lucrărilor publice și administrației nr. 442/2022, nr. 443/2022, nr. 444/2022, nr. 440/2022 și nr. 441/2022",
      "documents": [
        {
          "date": "20-09-2022",
          "link": "https://www.mdlpa.ro/uploads/articole/attachments/6329c4f7477fe636885671.docx",
          "title": "Ordin pentru modificarea și completarea Ghidurilor Specifice – Condiții de accesare a fondurilor europene aferente PNRR, Axa 1 – Schema de granturi pentru eficiență energetică și reziliență în clădiri rezidențiale multifamiliale (Operațiunea A.1 – Renovarea integrată (consolidare seismică și renovarea energetică moderată) a clădirilor rezidențiale multifamiliale; Operațiunea A.2 –  Renovarea energetică moderată a clădirilor rezidențiale multifamiliale pentru comunități expuse riscului de sărăcie și excluziune socială; Operațiunea A.3 - Renovarea energetică moderată sau aprofundată a clădirilor rezidențiale multifamiliale) și Axa 2 – Schema de granturi pentru eficiență energetică și reziliență în clădiri publice (Operațiunea B.1 - Renovarea integrată (consolidare seismică și renovare energetică moderată) a clădirilor publice și Operațiunea B.2 – Renovarea energetică moderată sau aprofundată a clădirilor), aprobate prin ordinele ministrului dezvoltării, lucrărilor publice și administrației nr. 442/2022, nr. 443/2022, nr. 444/2022, nr. 440/2022 și nr. 441/2022",
          "type": "doc"
        },
        {
          "date": "20-09-2022",
          "link": "https://www.mdlpa.ro/uploads/articole/attachments/6329c4f75be54320073596.docx",
          "title": "Referat de aprobare",
          "type": "doc"
        }
      ]
    },
    {
      "currentUrl": "https://www.mdlpa.ro/pages/proiecthgaprobarebugetrectificat2022anl",
      "date": "19-09-2022",
      "name": "Proiect de HG pentru aprobarea bugetului rectificat de venituri și cheltuieli pe anul 2022 al Agenției Naționale pentru Locuințe, instituție publică aflată sub autoritatea Ministerului Dezvoltării, Lucrărilor Publice și Administrației",
      "documents": [
        {
          "date": "19-09-2022",
          "link": "https://www.mdlpa.ro/uploads/articole/attachments/632876879579a292790653.docx",
          "title": "Hotărâre a Guvernului pentru aprobarea bugetului rectificat de venituri și cheltuieli pe anul 2022 al Agenției Naționale pentru Locuințe, instituție publică aflată sub autoritatea Ministerului Dezvoltării, Lucrărilor Publice și Administrației",
          "type": "doc"
        },
        {
          "date": "19-09-2022",
          "link": "https://www.mdlpa.ro/uploads/articole/attachments/63287687a5cc5402637552.docx",
          "title": "Nota de fundamentare",
          "type": "doc"
        },
        {
          "date": "19-09-2022",
          "link": "https://www.mdlpa.ro/uploads/articole/attachments/632876877ff9e934578845.ods",
          "title": "Anexa",
          "type": "xls"
        }
      ]
    },
    {
      "currentUrl": "https://www.mdlpa.ro/pages/proiecthgmodifcareanexa1hg3231996programspecialsprijinlocalitatimuntiiapuseni",
      "date": "19-09-2022",
      "name": "Proiect de HG pentru modificarea și completarea anexei nr. 1 la Hotărârea Guvernului nr. 323/1996 privind aprobarea Programului special pentru sprijinirea dezvoltării economico-sociale a unor localități din Munții Apuseni",
      "documents": [
        {
          "date": "19-09-2022",
          "link": "https://www.mdlpa.ro/uploads/articole/attachments/632873a3b10bd762715922.docx",
          "title": "Hotărâre a Guvernului pentru modificarea și completarea anexei nr. 1 la Hotărârea Guvernului nr. 323/1996 privind aprobarea Programului special pentru sprijinirea dezvoltării economico-sociale a unor localități din Munții Apuseni",
          "type": "doc"
        },
        {
          "date": "19-09-2022",
          "link": "https://www.mdlpa.ro/uploads/articole/attachments/632873a396f82481592534.docx",
          "title": "Nota de fundamentare",
          "type": "doc"
        }
      ]
    },
    {
      "currentUrl": "https://www.mdlpa.ro/pages/proiectlegemobilitateurbanadurabila",
      "date": "16-09-2022",
      "name": "Proiect de LEGE privind mobilitatea urbană durabilă",
      "documents": [
        {
          "date": "16-09-2022",
          "link": "https://www.mdlpa.ro/uploads/articole/attachments/63245d0aa7799863659829.docx",
          "title": "Lege privind mobilitatea urbană durabilă",
          "type": "doc"
        },
        {
          "date": "16-09-2022",
          "link": "https://www.mdlpa.ro/uploads/articole/attachments/63245d0a8ea24141620263.docx",
          "title": "Expunere de motive",
          "type": "doc"
        }
      ]
    },
    {
      "currentUrl": "https://www.mdlpa.ro/pages/proiecthgaprobarenormativecheltuieliorganizareforumcooperaredescentralizarerofrbrasov",
      "date": "13-09-2022",
      "name": "Proiect de HG privind aprobarea normativelor de cheltuieli aferente organizării și desfășurării în România a celei de-a șasea ediții a Forumului cooperării descentralizate româno-franceze, în perioada 03 – 05 noiembrie 2022, Brașov",
      "documents": [
        {
          "date": "13-09-2022",
          "link": "https://www.mdlpa.ro/uploads/articole/attachments/632056ea1226f564125282.docx",
          "title": "Hotărâre a Guvernului privind aprobarea normativelor de cheltuieli aferente organizării și desfășurării în România a celei de-a șasea ediții a Forumului cooperării descentralizate româno-franceze, în perioada 03 – 05 noiembrie 2022, Brașov",
          "type": "doc"
        },
        {
          "date": "13-09-2022",
          "link": "https://www.mdlpa.ro/uploads/articole/attachments/632056ea2719e090760948.doc",
          "title": "Nota de fundamentare",
          "type": "doc"
        },
        {
          "date": "13-09-2022",
          "link": "https://www.mdlpa.ro/uploads/articole/attachments/632056e9f0cba053236220.docx",
          "title": "Anexa",
          "type": "doc"
        }
      ]
    },
    {
      "currentUrl": "https://www.mdlpa.ro/pages/proiectdehgpentrumodificareanrcrt31dinanexahg10582009privindstabilirearegimuluijuridicalunorlocuintepentrutineri",
      "date": "01-09-2022",
      "name": "Proiect de HG pentru modificarea nr. crt.3.1. din anexa la HG nr.1.058/2009 privind stabilirea regimului juridic al unor locuinţe pentru tineri, destinate închirierii, construite prin programe de investiţii la nivel naţional şi aflate în administrarea consiliilor locale  precum şi a măsurilor necesare în vederea aplicării prevederilor Legii nr. 152/1998",
      "documents": [
        {
          "date": "01-09-2022",
          "link": "https://www.mdlpa.ro/uploads/articole/attachments/6310a9db05b29366881160.doc",
          "title": "Hotărâre",
          "type": "doc"
        },
        {
          "date": "01-09-2022",
          "link": "https://www.mdlpa.ro/uploads/articole/attachments/6310a9db05b29366881160.doc",
          "title": "a Guvernului pentru modificarea nr. crt. 3.1. din anexa la Hotărârea Guvernului nr. 1.058/2009 privind stabilirea regimului juridic al unor locuinţe pentru tineri, destinate închirierii, construite prin programe de investiţii la nivel naţional şi aflate în administrarea consiliilor locale, precum şi a măsurilor necesare în vederea aplicării prevederilor Legii nr. 152/1998 privind înfiinţarea Agenţiei Naţionale pentru Locuinţe, referitoare la administrarea şi vânzarea acestora.",
          "type": "doc"
        },
        {
          "date": "01-09-2022",
          "link": "https://www.mdlpa.ro/uploads/articole/attachments/6310a9dbb10cb610592013.doc",
          "title": "Nota de fundamentare",
          "type": "doc"
        }
      ]
    },
    {
      "currentUrl": "https://www.mdlpa.ro/pages/proiectdeordinpentrumodificareasicompletareanormelormetodologicedeaplicarealegii50199131082022",
      "date": "31-08-2022",
      "name": "Proiect de ORDIN pentru modificarea și completarea Normelor metodologice de aplicare a Legii nr. 50/1991 privind autorizarea executării lucrărilor de construcții, aprobate prin Ordinul ministrului dezvoltării regionale și locuinței nr. 839/2009",
      "documents": [
        {
          "date": "31-08-2022",
          "link": "https://www.mdlpa.ro/uploads/articole/attachments/630f0c72a53c4560392361.docx",
          "title": "Ordin pentru modificarea și completarea Normelor metodologice de aplicare a Legii nr. 50/1991 privind autorizarea executării lucrărilor de construcții, aprobate prin Ordinul ministrului dezvoltării regionale și locuinței nr. 839/2009.",
          "type": "doc"
        },
        {
          "date": "31-08-2022",
          "link": "https://www.mdlpa.ro/uploads/articole/attachments/630f0c7305ed4725866132.doc",
          "title": "Referat de aprobare",
          "type": "doc"
        }
      ]
    },
    {
      "currentUrl": "https://www.mdlpa.ro/pages/proiectougreglementaremasuriimplementarepnrr19082022",
      "date": "19-08-2022",
      "name": "Proiect de OUG privind reglementarea unor măsuri de implementare a Programului Național de Redresare și Reziliență în domeniul gestionării deșeurilor municipale, precum şi modificarea unor acte normative",
      "documents": [
        {
          "date": "19-08-2022",
          "link": "https://www.mdlpa.ro/uploads/articole/attachments/62ff68780b131838490830.docx",
          "title": "Ordonanță de urgență a Guvernului privind reglementarea unor măsuri de implementare a Programului Național de Redresare și Reziliență în domeniul gestionării deșeurilor municipale, precum şi modificarea unor acte normative",
          "type": "doc"
        },
        {
          "date": "19-08-2022",
          "link": "https://www.mdlpa.ro/uploads/articole/attachments/62ff6877e28ae495540163.docx",
          "title": "Nota de fundamentare",
          "type": "doc"
        },
        {
          "date": "19-08-2022",
          "link": "https://www.mdlpa.ro/uploads/articole/attachments/6322f4a7e8a3b282969057.docx",
          "title": "Versiunea îmbunătățită - publicată în 15.09.2022",
          "type": "doc"
        }
      ]
    },
    {
      "currentUrl": "https://www.mdlpa.ro/pages/proiectogstabiliremasuripndl118082022",
      "date": "18-08-2022",
      "name": "Proiect de OG pentru stabilirea unor măsuri pentru derularea Programului național de dezvoltare locală etapa I",
      "documents": [
        {
          "date": "18-08-2022",
          "link": "https://www.mdlpa.ro/uploads/articole/attachments/62fe45b856d56300399770.doc",
          "title": "Ordonanță a Guvernului",
          "type": "doc"
        },
        {
          "date": "18-08-2022",
          "link": "https://www.mdlpa.ro/uploads/articole/attachments/62fe45b856d56300399770.doc",
          "title": "pentru stabilirea unor măsuri pentru derularea Programului național de dezvoltare locală etapa I",
          "type": "doc"
        },
        {
          "date": "18-08-2022",
          "link": "https://www.mdlpa.ro/uploads/articole/attachments/62fe45b8364c4204528246.doc",
          "title": "Nota de fundamentare",
          "type": "doc"
        }
      ]
    },
    {
      "currentUrl": "https://www.mdlpa.ro/pages/HGUNCJRutilitatepublica",
      "date": "12-08-2022",
      "name": "Proiect de HG privind recunoaşterea Uniunii Naționale a Consiliilor Județene din România ca fiind de utilitate publică",
      "documents": [
        {
          "date": "12-08-2022",
          "link": "https://www.mdlpa.ro/uploads/articole/attachments/62f6277fb1c18796646232.doc",
          "title": "Hotărâre a Guvernului privind recunoaşterea Uniunii Naționale a Consiliilor Județene din România ca fiind de utilitate publică",
          "type": "doc"
        },
        {
          "date": "12-08-2022",
          "link": "https://www.mdlpa.ro/uploads/articole/attachments/62f6277fc3101610332410.DOC",
          "title": "Nota de fundamentare",
          "type": "doc"
        }
      ]
    },
    {
      "currentUrl": "https://www.mdlpa.ro/pages/proiectordinprocedurarestituirelegea2572022",
      "date": "01-08-2022",
      "name": "Proiect de ORDIN privind Procedura de restituire în baza art. 3 din Legea nr. 257/2022 privind stabilirea unor măsuri referitoare la executarea sancţiunilor contravenţionale aplicate în temeiul art. 4 alin. (1) din Ordonanţa de urgenţă a Guvernului nr. 129/2021 privind implementarea formularului digital de intrare în România, abrogată prin Ordonanţa de urgenţă a Guvernului nr. 22/2022 pentru abrogarea Ordonanţei de urgenţă a Guvernului nr. 129/2021 privind implementarea formularului digital de intrare în România",
      "documents": [
        {
          "date": "01-08-2022",
          "link": "https://www.mdlpa.ro/uploads/articole/attachments/62ebc32d91f84688829694.docx",
          "title": "Ordin privind Procedura de restituire în baza art. 3 din Legea nr. 257/2022 privind stabilirea unor măsuri referitoare la executarea sancţiunilor contravenţionale aplicate în temeiul art. 4 alin. (1) din Ordonanţa de urgenţă a Guvernului nr. 129/2021 privind implementarea formularului digital de intrare în România, abrogată prin Ordonanţa de urgenţă a Guvernului nr. 22/2022 pentru abrogarea Ordonanţei de urgenţă a Guvernului nr. 129/2021 privind implementarea formularului digital de intrare în România",
          "type": "doc"
        },
        {
          "date": "01-08-2022",
          "link": "https://www.mdlpa.ro/uploads/articole/attachments/62ebc32dadb9c201701458.docx",
          "title": "Referat de aprobare",
          "type": "doc"
        },
        {
          "date": "01-08-2022",
          "link": "https://www.mdlpa.ro/uploads/articole/attachments/62ebc32d4aefe629443847.docx",
          "title": "Anexa 1",
          "type": "doc"
        },
        {
          "date": "01-08-2022",
          "link": "https://www.mdlpa.ro/uploads/articole/attachments/62ebc32d6a8ba447968258.doc",
          "title": "Anexa 2",
          "type": "doc"
        }
      ]
    },
    {
      "currentUrl": "https://www.mdlpa.ro/pages/proiectogmodificarelegea1521998infiintareanl2022",
      "date": "01-08-2022",
      "name": "Proiect de OG pentru modificarea Legii nr. 152/1998 privind înfiinţarea Agenţiei Naţionale pentru Locuinţe",
      "documents": [
        {
          "date": "01-08-2022",
          "link": "https://www.mdlpa.ro/uploads/articole/attachments/62e7d2626ec56677284988.doc",
          "title": "Ordonanță a Guvernului pentru modificarea Legii nr. 152/1998 privind înfiinţarea Agenţiei Naţionale pentru Locuinţe",
          "type": "doc"
        },
        {
          "date": "01-08-2022",
          "link": "https://www.mdlpa.ro/uploads/articole/attachments/62e7d26259be5044257350.doc",
          "title": "Nota de fundamentare",
          "type": "doc"
        },
        {
          "date": "01-08-2022",
          "link": "https://www.mdlpa.ro/uploads/articole/attachments/62e7d2627c284285811865.doc",
          "title": "Tabel comparativ",
          "type": "doc"
        }
      ]
    },
    {
      "currentUrl": "https://www.mdlpa.ro/pages/proiectogstabiliremasuriindeplinirejaloanepnrrc10c11c14c15",
      "date": "01-08-2022",
      "name": "Proiect de OG privind stabilirea unor măsuri necesare pentru îndeplinirea jaloanelor și țintelor din Planul Național de Redresare și Reziliență aferente Componentei 10 - Fondul local, Componentei 11- Turism și Cultură, Componentei 14 – Buna guvernanță și Componentei 15 – Educație",
      "documents": [
        {
          "date": "01-08-2022",
          "link": "https://www.mdlpa.ro/uploads/articole/attachments/62e7cf1ab4d91603037973.doc",
          "title": "Ordonanță a Guvernului privind stabilirea unor măsuri necesare pentru îndeplinirea jaloanelor și țintelor din Planul Național de Redresare și Reziliență aferente Componentei 10 - Fondul local, Componentei 11- Turism și Cultură, Componentei 14 – Buna guvernanță și Componentei 15 – Educație",
          "type": "doc"
        },
        {
          "date": "01-08-2022",
          "link": "https://www.mdlpa.ro/uploads/articole/attachments/62e7cf1a8b3e7407182712.docx",
          "title": "Nota de fundamentare",
          "type": "doc"
        }
      ]
    },
    {
      "currentUrl": "https://www.mdlpa.ro/pages/proiectogmodificareog252001infiintarecni22072022",
      "date": "22-07-2022",
      "name": "Proiect de OG pentru modificarea și completarea Ordonanței Guvernului nr. 25/2001 privind înființarea Companiei Naționale de Investiții \"C.N.I.\" - S.A.",
      "documents": [
        {
          "date": "22-07-2022",
          "link": "https://www.mdlpa.ro/uploads/articole/attachments/62da903612f45715328933.docx",
          "title": "Ordonanță a Guvernului pentru modificarea și completarea Ordonanței Guvernului nr. 25/2001 privind înființarea Companiei Naționale de Investiții \"C.N.I.\" - S.A.",
          "type": "doc"
        },
        {
          "date": "22-07-2022",
          "link": "https://www.mdlpa.ro/uploads/articole/attachments/62da903636eba162879291.docx",
          "title": "Nota de fundamentare",
          "type": "doc"
        }
      ]
    },
    {
      "currentUrl": "https://www.mdlpa.ro/pages/proiectordinaplicarebucurestiog362006functionaresistemecentralizatealimentareenergietermica",
      "date": "22-07-2022",
      "name": "Proiect de ORDIN pentru aplicarea la nivelul municipiului București a prevederilor art. 3 alin. (5) din Ordonanţa Guvernului nr. 36/2006 privind unele măsuri pentru funcţionarea sistemelor centralizate de alimentare cu energie termică a populaţiei",
      "documents": [
        {
          "date": "22-07-2022",
          "link": "https://www.mdlpa.ro/uploads/articole/attachments/62da6cbe7a157967043171.docx",
          "title": "Ordin pentru aplicarea la nivelul municipiului București a prevederilor art. 3 alin. (5)  din Ordonanţa Guvernului nr. 36/2006 privind unele măsuri pentru funcţionarea sistemelor centralizate de alimentare cu energie termică a populaţiei",
          "type": "doc"
        },
        {
          "date": "22-07-2022",
          "link": "https://www.mdlpa.ro/uploads/articole/attachments/62da6cbe8e4e6528589227.docx",
          "title": "Referat de aprobare",
          "type": "doc"
        }
      ]
    },
    {
      "currentUrl": "https://www.mdlpa.ro/pages/proiectougmodificareoug572019",
      "date": "19-07-2022",
      "name": "Proiect de OUG pentru modificarea Ordonanței de urgență a Guvernului nr. 57/2019 privind Codul administrativ",
      "documents": [
        {
          "date": "19-07-2022",
          "link": "https://www.mdlpa.ro/uploads/articole/attachments/62d684050d250647171297.doc",
          "title": "Ordonanță de urgență a Guvernului pentru modificarea Ordonanței de urgență a Guvernului nr. 57/2019 privind Codul administrativ",
          "type": "doc"
        },
        {
          "date": "19-07-2022",
          "link": "https://www.mdlpa.ro/uploads/articole/attachments/62d68405254d3706418043.docx",
          "title": "Nota de fundamentare",
          "type": "doc"
        }
      ]
    },
    {
      "currentUrl": "https://www.mdlpa.ro/pages/proiectordinnormativproiectareinstalatisanitare",
      "date": "18-07-2022",
      "name": "Proiect de ORDIN pentru aprobarea reglementării tehnice „Normativ privind proiectarea, execuţia şi exploatarea instalaţiilor sanitare aferente clădirilor, Indicativ I9-2022”",
      "documents": [
        {
          "date": "18-07-2022",
          "link": "https://www.mdlpa.ro/uploads/articole/attachments/62d52e24e8336291709483.doc",
          "title": "Ordin pentru aprobarea reglementării tehnice „Normativ privind proiectarea, execuţia şi exploatarea instalaţiilor sanitare aferente clădirilor, Indicativ I9-2022”",
          "type": "doc"
        },
        {
          "date": "18-07-2022",
          "link": "https://www.mdlpa.ro/uploads/articole/attachments/62d52e255fdf4150614777.doc",
          "title": "Referat de aprobare",
          "type": "doc"
        }
      ]
    },
    {
      "currentUrl": "https://www.mdlpa.ro/pages/proiectdehgpentruabrogareahg1723privindaprobareaprogramuluidemasuripentrucombatereabirocratieiinactivitateaderelatiicupublicul14072022",
      "date": "14-07-2022",
      "name": "Proiect de HG pentru abrogarea HG nr. 1723/2004 privind aprobarea Programului de măsuri pentru combaterea birocrației în activitatea de relații cu publicul, cu modificările și completările ulterioare",
      "documents": [
        {
          "date": "14-07-2022",
          "link": "https://www.mdlpa.ro/uploads/articole/attachments/62cfc7388866c643636484.docx",
          "title": "Hotărâre a Guvernului  pentru abrogarea Hotărârii Guvernului nr. 1723/2004 privind aprobarea Programului de măsuri pentru combaterea birocrației în activitatea de relații cu publicul, cu modificările și completările ulterioare.",
          "type": "doc"
        },
        {
          "date": "14-07-2022",
          "link": "https://www.mdlpa.ro/uploads/articole/attachments/62cfc73868fd0981863849.docx",
          "title": "Notă de funfamentare",
          "type": "doc"
        }
      ]
    },
    {
      "currentUrl": "https://www.mdlpa.ro/pages/proiectougstabiliremasurifinalizarelucrarilocuinte",
      "date": "08-07-2022",
      "name": "Proiect de OG pentru stabilirea unor măsuri privind finalizarea lucrărilor de intervenție pentru creșterea performanței energetice la blocurile de locuințe din cadrul Programului național multianual privind creșterea performanței energetice a blocurilor de locuințe cu finanțare în perioada 2019-2021",
      "documents": [
        {
          "date": "08-07-2022",
          "link": "https://www.mdlpa.ro/uploads/articole/attachments/62c815fdaf5ea780361778.doc",
          "title": "Ordonanță a Guvernului pentru stabilirea unor măsuri privind finalizarea lucrărilor de intervenție pentru creșterea performanței energetice la blocurile de locuințe din cadrul Programului național multianual privind creșterea performanței energetice a blocurilor de locuințe cu finanțare în perioada 2019-2021",
          "type": "doc"
        },
        {
          "date": "08-07-2022",
          "link": "https://www.mdlpa.ro/uploads/articole/attachments/62c815fd9cab3209288636.doc",
          "title": "Nota de fundamentare",
          "type": "doc"
        }
      ]
    },
    {
      "currentUrl": "https://www.mdlpa.ro/pages/proiecthgdesfiintarespitalmm",
      "date": "08-07-2022",
      "name": "Proiect de HG privind desfiinţarea Spitalului de Boli Cronice Baia Sprie, judeţul Maramureş",
      "documents": [
        {
          "date": "08-07-2022",
          "link": "https://www.mdlpa.ro/uploads/articole/attachments/62c7ddd238b48326652615.docx",
          "title": "Hotărâre a Guvernului privind desfiinţarea Spitalului de Boli Cronice Baia Sprie, judeţul Maramureş",
          "type": "doc"
        },
        {
          "date": "08-07-2022",
          "link": "https://www.mdlpa.ro/uploads/articole/attachments/62c7ddd221e92137056529.docx",
          "title": "Nota de fundamentare",
          "type": "doc"
        }
      ]
    },
    {
      "currentUrl": "https://www.mdlpa.ro/pages/proiecthgaprobarenormeformareperfectionarefunctionaripublici",
      "date": "08-07-2022",
      "name": "Proiect de HG pentru aprobarea normelor metodologice cu privire la formarea și perfecționarea profesională a funcționarilor publici, inclusiv drepturile și obligațiile asociate procesului de formare, precum și a normelor privind sistemul de credite necesar promovării funcționarilor publici în grad profesional și într-o funcție publică de conducere vacantă",
      "documents": [
        {
          "date": "08-07-2022",
          "link": "https://www.mdlpa.ro/uploads/articole/attachments/62c7d7523e0dd244927679.doc",
          "title": "Hotărâre a Guvernului pentru aprobarea normelor metodologice cu privire la formarea și perfecționarea profesională a funcționarilor publici, inclusiv drepturile și obligațiile asociate procesului de formare, precum și a normelor privind sistemul de credite necesar promovării funcționarilor publici în grad profesional și într-o funcție publică de conducere vacantă",
          "type": "doc"
        },
        {
          "date": "08-07-2022",
          "link": "https://www.mdlpa.ro/uploads/articole/attachments/62c7d752a8fae644799234.doc",
          "title": "Nota de fundamentare",
          "type": "doc"
        }
      ]
    },
    {
      "currentUrl": "https://www.mdlpa.ro/pages/proiectordinaprobarereglementarecanalizatiitelecomubnicatiifibraoptica",
      "date": "04-07-2022",
      "name": "Proiect de ORDIN pentru aprobarea reglementării tehnice „Canalizații de telecomunicații (CTc). Fibră optică. Proiectare, execuție, utilizare, întreținere și verificare, indicativ RTC - 5”",
      "documents": [
        {
          "date": "04-07-2022",
          "link": "https://www.mdlpa.ro/uploads/articole/attachments/62c28d966b0ab348750516.doc",
          "title": "Ordin pentru aprobarea reglementării tehnice „Canalizații de telecomunicații (CTc). Fibră optică. Proiectare, execuție, utilizare, întreținere și verificare, indicativ RTC - 5”",
          "type": "doc"
        },
        {
          "date": "04-07-2022",
          "link": "https://www.mdlpa.ro/uploads/articole/attachments/62c28d9684bda893237846.doc",
          "title": "Referat de aprobare",
          "type": "doc"
        },
        {
          "date": "04-07-2022",
          "link": "https://www.mdlpa.ro/uploads/articole/attachments/62c28d9657216705823062.docx",
          "title": "Anexa",
          "type": "doc"
        }
      ]
    },
    {
      "currentUrl": "https://www.mdlpa.ro/pages/proiectordinmodificarecompletarereglementarenormativiluminatrutierpietonal",
      "date": "04-07-2022",
      "name": "Proiect de ORDIN pentru modificarea și completarea reglementării tehnice „Normativ pentru proiectarea sistemelor de iluminat rutier și pietonal, indicativ NP 062/2002”",
      "documents": [
        {
          "date": "04-07-2022",
          "link": "https://www.mdlpa.ro/uploads/articole/attachments/62c28cddbe584824346922.doc",
          "title": "Ordin pentru modificarea și completarea reglementării tehnice „Normativ pentru proiectarea sistemelor de iluminat rutier și pietonal, indicativ NP 062/2002”",
          "type": "doc"
        },
        {
          "date": "04-07-2022",
          "link": "https://www.mdlpa.ro/uploads/articole/attachments/62c28cddadc2a829114050.doc",
          "title": "Referat de aprobare",
          "type": "doc"
        }
      ]
    },
    {
      "currentUrl": "https://www.mdlpa.ro/pages/proiectordinaprobarereglementarenormativiluminatartificialcladiri",
      "date": "01-07-2022",
      "name": "Proiect de ORDIN pentru aprobarea modificării și completării reglementării tehnice „Normativ pentru proiectarea și executarea sistemelor de iluminat artificial din clădiri, indicativ NP 061/2002”",
      "documents": [
        {
          "date": "01-07-2022",
          "link": "https://www.mdlpa.ro/uploads/articole/attachments/62bed38de0002532994660.doc",
          "title": "Ordin pentru aprobarea modificării și completării reglementării tehnice „Normativ pentru proiectarea și executarea sistemelor de iluminat artificial din clădiri, indicativ NP 061/2002”",
          "type": "doc"
        },
        {
          "date": "01-07-2022",
          "link": "https://www.mdlpa.ro/uploads/articole/attachments/62bed38e06589404753120.doc",
          "title": "Referat de aprobare",
          "type": "doc"
        }
      ]
    },
    {
      "currentUrl": "https://www.mdlpa.ro/pages/proiectordinmodificarecompletarereglementarenormativinstalatiiincalzirecentrala",
      "date": "01-07-2022",
      "name": "Proiect de ORDIN pentru modificarea și completarea reglementării tehnice „Normativ pentru proiectarea, executarea şi exploatarea instalațiilor de încălzire centrală, Indicativ I 13-2015”",
      "documents": [
        {
          "date": "01-07-2022",
          "link": "https://www.mdlpa.ro/uploads/articole/attachments/62bed1c0044f0745486840.doc",
          "title": "Ordin pentru modificarea și completarea reglementării tehnice „Normativ pentru proiectarea, executarea şi exploatarea instalațiilor de încălzire centrală, Indicativ I 13-2015”",
          "type": "doc"
        },
        {
          "date": "01-07-2022",
          "link": "https://www.mdlpa.ro/uploads/articole/attachments/62bed1c020ff2885179103.doc",
          "title": "Referat de aprobare",
          "type": "doc"
        }
      ]
    },
    {
      "currentUrl": "https://www.mdlpa.ro/pages/proiectordinaprobarereglementaretehnicanormativinstalatiiventilareclimnatizare",
      "date": "01-07-2022",
      "name": "Proiect de ORDIN pentru aprobarea reglementării tehnice „Normativ pentru proiectarea, executarea și exploatarea instalațiilor de ventilare și climatizare, Indicativ I5-2022”",
      "documents": [
        {
          "date": "01-07-2022",
          "link": "https://www.mdlpa.ro/uploads/articole/attachments/62bed0d43fee0533450042.doc",
          "title": "Ordin pentru aprobarea reglementării tehnice „Normativ pentru proiectarea, executarea și exploatarea instalațiilor de ventilare și climatizare, Indicativ I5-2022”",
          "type": "doc"
        },
        {
          "date": "01-07-2022",
          "link": "https://www.mdlpa.ro/uploads/articole/attachments/62bed0d459f56236267165.doc",
          "title": "Referat de aprobare",
          "type": "doc"
        },
        {
          "date": "01-07-2022",
          "link": "https://www.mdlpa.ro/uploads/articole/attachments/62bed0d4275d9800858298.docx",
          "title": "Anexa",
          "type": "doc"
        }
      ]
    }
  ]
}