{
  "mae": [
    {
      "currentUrl": "https://www.mae.ro/node/2011",
      "date": "25-07-2023",
      "name": "HOTĂRÂRE privind alocarea unor sume din Fondul de rezervă bugetară la dispoziția Guvernului, prevăzut în bugetul de stat pe anul 2023, pentru suplimentarea bugetului Ministerului Afacerilor Externe",
      "documents": [
        {
          "date": "25-07-2023",
          "link": "https://www.mae.ro/sites/default/files/file/anul_2023/pdf_2023/2023.07.25_proiect_hg_suplimentare_buget_mae_iulie_2023.pdf",
          "title": "HOTĂRÂRE privind alocarea unor sume din Fondul de rezervă bugetară la dispoziția Guvernului, prevăzut în bugetul de stat pe anul 2023, pentru suplimentarea bugetului Ministerului Afacerilor Externe",
          "type": "pdf"
        },
        {
          "date": "25-07-2023",
          "link": "https://www.mae.ro/sites/default/files/file/anul_2023/pdf_2023/2023.07.25_nota_de_fundamentare_proiect_hg_suplimentare_buget_mae_iulie_2023.pdf",
          "title": "NOTĂ DE FUNDAMENTARE",
          "type": "pdf"
        }
      ]
    },
    {
      "currentUrl": "https://www.mae.ro/node/2011",
      "date": "21-07-2023",
      "name": "HOTĂRÂRE pentru aprobarea plății contribuției financiare voluntare a României la bugetul Organizației pentru Cooperare și Dezvoltare Economică (OCDE), destinată Programului Regional de Competitivitate EURASIA",
      "documents": [
        {
          "date": "21-07-2023",
          "link": "https://www.mae.ro/sites/default/files/file/anul_2023/pdf_2023/2023.07.21_proiect_hg_contributie_voluntara_program_eurasia_var_4.07.pdf",
          "title": "HOTĂRÂRE pentru aprobarea plății contribuției financiare voluntare a României la bugetul Organizației pentru Cooperare și Dezvoltare Economică (OCDE), destinată Programului Regional de Competitivitate EURASIA",
          "type": "pdf"
        },
        {
          "date": "21-07-2023",
          "link": "https://www.mae.ro/sites/default/files/file/anul_2023/pdf_2023/2023.07.21_nf_eurasia.pdf",
          "title": "NOTĂ DE FUND",
          "type": "pdf"
        },
        {
          "date": "21-07-2023",
          "link": "https://www.mae.ro/sites/default/files/file/anul_2023/pdf_2023/2023.07.21_nf_eurasia.pdf",
          "title": "A",
          "type": "pdf"
        },
        {
          "date": "21-07-2023",
          "link": "https://www.mae.ro/sites/default/files/file/anul_2023/pdf_2023/2023.07.21_nf_eurasia.pdf",
          "title": "MENTARE",
          "type": "pdf"
        }
      ]
    },
    {
      "currentUrl": "https://www.mae.ro/node/2011",
      "date": "21-07-2023",
      "name": "HOTĂRÂRE pentru aprobarea contribuţiilor voluntare ale României către următoarele fonduri voluntare ale Organizaţiei Tratatului Atlanticului de Nord: Fondul voluntar de consolidare a capacităţii de apărare a Republicii Moldova (Moldova DCB Trust Fund) şi Fondul voluntar privind Pachetul de Asistenţă Cuprinzătoare pentru Ucraina (NATO-Ukraine Comprehensive Assistance Package Trust Fund)",
      "documents": [
        {
          "date": "21-07-2023",
          "link": "https://www.mae.ro/sites/default/files/file/anul_2023/pdf_2023/2023.07.21_hg_contributii_dcb_rmd_cap_ukr.pdf",
          "title": "HOTĂRÂRE pentru aprobarea contribuţiilor voluntare ale României către următoarele fonduri voluntare ale Organizaţiei Tratatului Atlanticului de Nord: Fondul voluntar de consolidare a capacităţii de apărare a Republicii Moldova (Moldova DCB Trust Fund) şi Fondul voluntar privind Pachetul de Asistenţă Cuprinzătoare pentru Ucraina (NATO-Ukraine Comprehensive Assistance Package Trust Fund)",
          "type": "pdf"
        },
        {
          "date": "21-07-2023",
          "link": "https://www.mae.ro/sites/default/files/file/anul_2023/pdf_2023/2023.07.21_nf_contributii_dcb_rmd_cap_ukr.pdf",
          "title": "NOTĂ DE FUNDAMENTARE",
          "type": "pdf"
        }
      ]
    },
    {
      "currentUrl": "https://www.mae.ro/node/2011",
      "date": "25-05-2023",
      "name": "HOTĂRÂRE pentru înscrierea unui imobil în inventarul centralizat al bunurilor din domeniul public al statului, și darea în administrarea Ministerului Afacerilor Externe",
      "documents": [
        {
          "date": "25-05-2023",
          "link": "https://www.mae.ro/sites/default/files/file/anul_2023/pdf_2023/2023.05.25_hg_centralizare_bunuri_mae.pdf",
          "title": "HOTĂRÂRE pentru înscrierea unui imobil în inventarul centralizat al bunurilor din domeniul public al statului, și darea în administrarea Ministerului Afacerilor Externe",
          "type": "pdf"
        },
        {
          "date": "25-05-2023",
          "link": "https://www.mae.ro/sites/default/files/file/anul_2023/pdf_2023/2023.05.25_nf_centralizare_bunuri_mae.pdf",
          "title": "NOTĂ DE FUNDAMENTARE",
          "type": "pdf"
        },
        {
          "date": "25-05-2023",
          "link": "https://www.mae.ro/sites/default/files/file/anul_2023/pdf_2023/2023.05.25_anexa_centralizare_bunuri_mae.pdf",
          "title": "ANEXĂ",
          "type": "pdf"
        }
      ]
    },
    {
      "currentUrl": "https://www.mae.ro/node/2011",
      "date": "17-05-2023",
      "name": "LEGE pentru aderarea României la Tratatul de prietenie și cooperare în Asia de Sud-Est, adoptat la Denpasar, Indonezia, la 24 februarie 1976, care a intrat în vigoare la 15 iulie 1976",
      "documents": [
        {
          "date": "17-05-2023",
          "link": "https://www.mae.ro/sites/default/files/file/anul_2023/pdf_2023/2023.05.17_proiect_lege_aderare.pdf",
          "title": "LEGE pentru aderarea României la Tratatul de prietenie și cooperare în Asia de Sud-Est, adoptat la Denpasar, Indonezia, la 24 februarie 1976, care a intrat în vigoare la 15 iulie 1976",
          "type": "pdf"
        },
        {
          "date": "17-05-2023",
          "link": "https://www.mae.ro/sites/default/files/file/anul_2023/pdf_2023/2023.05.17_expunere_de_motive_lege_aderare_tac.pdf",
          "title": "EXPUNERE DE MOTIVE",
          "type": "pdf"
        }
      ]
    },
    {
      "currentUrl": "https://www.mae.ro/node/2011",
      "date": "11-05-2023",
      "name": "LEGE pentru ratificarea Acordului între Guvernul României și Guvernul Republicii India privind dobândirea, pe bază de reciprocitate, a drepturilor de proprietate asupra terenurilor pentru buna funcționare a misiunilor diplomatice și oficiilor consulare, semnat la New Delhi, la 31 ianuarie 2023",
      "documents": [
        {
          "date": "11-05-2023",
          "link": "https://www.mae.ro/sites/default/files/file/anul_2023/pdf_2023/2023.05.11_proiect_lege_acord_ro-ind_terenuri.pdf",
          "title": "LEGE pentru ratificarea Acordului între Guvernul României și Guvernul Republicii India privind dobândirea, pe bază de reciprocitate, a drepturilor de proprietate asupra terenurilor pentru buna funcționare a misiunilor diplomatice și oficiilor consulare, semnat la New Delhi, la 31 ianuarie 2023",
          "type": "pdf"
        },
        {
          "date": "11-05-2023",
          "link": "https://www.mae.ro/sites/default/files/file/anul_2023/pdf_2023/2023.05.11_expunere_motive_lege_ac._ro-ind_terenuri.pdf",
          "title": "EXPUNERE DE MOTIVE",
          "type": "pdf"
        }
      ]
    },
    {
      "currentUrl": "https://www.mae.ro/node/2011",
      "date": "5-05-2023",
      "name": "HOTĂRÂRE pentru aprobarea cuantumului și a plății contribuției financiare voluntare a României la Fondul Special destinat sprijinirii activității Grefei Curții Europene a Drepturilor Omului",
      "documents": [
        {
          "date": "5-05-2023",
          "link": "https://www.mae.ro/sites/default/files/file/anul_2023/pdf_2023/proiect_hg.pdf",
          "title": "HOTĂRÂRE pentru aprobarea cuantumului și a plății contribuției financiare voluntare a României la Fondul Special destinat sprijinirii activității Grefei Curții Europene a Drepturilor Omului",
          "type": "pdf"
        },
        {
          "date": "5-05-2023",
          "link": "https://www.mae.ro/sites/default/files/file/anul_2023/pdf_2023/nota_de_fundamentare-1.pdf",
          "title": "NOTĂ DE FUNDAMENTARE",
          "type": "pdf"
        }
      ]
    },
    {
      "currentUrl": "https://www.mae.ro/node/2011",
      "date": "17-03-2023",
      "name": "HOTĂRÂRE pentru aprobarea Listei cuprinzând produsele militare supuse regimului de control al exporturilor, importurilor şi altor operaţiuni",
      "documents": [
        {
          "date": "17-03-2023",
          "link": "https://www.mae.ro/sites/default/files/file/anul_2023/pdf_2023/hg_si_anexa_lista.pdf",
          "title": "HOTĂRÂRE pentru aprobarea Listei cuprinzând produsele militare supuse regimului de control al exporturilor, importurilor şi altor operaţiuni",
          "type": "pdf"
        },
        {
          "date": "17-03-2023",
          "link": "https://www.mae.ro/sites/default/files/file/anul_2023/pdf_2023/nota_de_fundamentare.pdf",
          "title": "NOTĂ DE FUNDAMENTARE",
          "type": "pdf"
        }
      ]
    },
    {
      "currentUrl": "https://www.mae.ro/node/2011",
      "date": "14-03-2023",
      "name": "HOTĂRÂRE privind aprobarea plății contribuției voluntare a României la bugetul Secretariatului Consiliului Cooperării Regionale pentru anul 2023",
      "documents": [
        {
          "date": "14-03-2023",
          "link": "https://www.mae.ro/sites/default/files/file/anul_2023/pdf_2023/2023.03.14_proiect_hg_contrib_rcc.pdf",
          "title": "HOTĂRÂRE privind aprobarea plății contribuției voluntare a României la bugetul Secretariatului Consiliului Cooperării Regionale pentru anul 2023",
          "type": "pdf"
        },
        {
          "date": "14-03-2023",
          "link": "https://www.mae.ro/sites/default/files/file/anul_2023/pdf_2023/2023.03.14_nf_hg_rcc.pdf",
          "title": "NOTĂ DE FUNDAMENTARE",
          "type": "pdf"
        }
      ]
    },
    {
      "currentUrl": "https://www.mae.ro/node/2011",
      "date": "27-02-2023",
      "name": "HOTĂRÂRE pentru modificarea și completarea Hotărârii Guvernului nr. 492/2004 privind organizarea şi funcționarea institutelor culturale românești din străinătate prin reorganizarea centrelor culturale din străinătate, precum şi înființarea unor institute noi",
      "documents": [
        {
          "date": "27-02-2023",
          "link": "https://www.mae.ro/sites/default/files/file/anul_2023/pdf_2023/proiect_hg_492.2004_fără_posturi-f.pdf",
          "title": "HOTĂRÂRE pentru modificarea și completarea Hotărârii Guvernului nr. 492/2004 privind organizarea şi funcționarea institutelor culturale românești din străinătate prin reorganizarea centrelor culturale din străinătate, precum şi înființarea unor institute noi",
          "type": "pdf"
        },
        {
          "date": "27-02-2023",
          "link": "https://www.mae.ro/sites/default/files/file/anul_2023/pdf_2023/nf_hg_492.2004_fără_posturi-_final.pdf",
          "title": "NOTĂ DE FUNDAMENTARE",
          "type": "pdf"
        }
      ]
    },
    {
      "currentUrl": "https://www.mae.ro/node/2011",
      "date": "24-02-2023",
      "name": "HOTĂRÂRE pentru aprobarea Programului de cooperare între Guvernul României şi Guvernul Republicii Portugheze în domeniile limbii, educaţiei, ştiinţei, tehnologiei şi învăţământului superior, culturii, sportului, tineretului, mass-media, semnat la Bucureşti, la 7 septembrie 2022",
      "documents": [
        {
          "date": "24-02-2023",
          "link": "https://www.mae.ro/sites/default/files/file/anul_2023/pdf_2023/proiect_hg_acord_ro-portugalia.pdf",
          "title": "HOTĂRÂRE pentru aprobarea Programului de cooperare între Guvernul României şi Guvernul Republicii Portugheze în domeniile limbii, educaţiei, ştiinţei, tehnologiei şi învăţământului superior, culturii, sportului, tineretului, mass-media, semnat la Bucureşti, la 7 septembrie 2022",
          "type": "pdf"
        },
        {
          "date": "24-02-2023",
          "link": "https://www.mae.ro/sites/default/files/file/anul_2023/pdf_2023/nf_aprobare_program_ro-por.pdf",
          "title": "NOTĂ DE FUNDAMENTARE",
          "type": "pdf"
        }
      ]
    },
    {
      "currentUrl": "https://www.mae.ro/node/2011",
      "date": "20-02-2023",
      "name": "LEGE pentru ratificarea Convenției Internaționale pentru protecția tuturor persoanelor împotriva disparițiilor forțate, adoptată la New York, la 20 decembrie 2006, deschisă spre semnare la 6 februarie 2007, semnată de România la 3 decembrie 2008",
      "documents": [
        {
          "date": "20-02-2023",
          "link": "https://www.mae.ro/sites/default/files/file/anul_2023/pdf_2023/2023.02.20_proiect_lege_ratificare_conventie_.pdf",
          "title": "LEGE pentru ratificarea Convenției Internaționale pentru protecția tuturor persoanelor împotriva disparițiilor forțate, adoptată la New York, la 20 decembrie 2006, deschisă spre semnare la 6 februarie 2007, semnată de România la 3 decembrie 2008",
          "type": "pdf"
        },
        {
          "date": "20-02-2023",
          "link": "https://www.mae.ro/sites/default/files/file/anul_2023/pdf_2023/2023.02.20_expunere_de_motive_conventie.pdf",
          "title": "EXPUNERE DE MOTIVE",
          "type": "pdf"
        },
        {
          "date": "20-02-2023",
          "link": "https://www.mae.ro/sites/default/files/file/anul_2023/pdf_2023/2023.02.20_conventie_ro.pdf",
          "title": "CONVENȚIE",
          "type": "pdf"
        }
      ]
    },
    {
      "currentUrl": "https://www.mae.ro/node/2011",
      "date": "16-02-2023",
      "name": "ORDIN privind aprobarea Regulamentului de funcționare a Comisiei Naționale de Drept Internațional Umanitar",
      "documents": [
        {
          "date": "16-02-2023",
          "link": "https://www.mae.ro/sites/default/files/file/anul_2023/pdf_2023/2023.02.16_proiect_ordin_rof_cndiu.pdf",
          "title": "ORDIN privind aprobarea Regulamentului de funcționare a Comisiei Naționale de Drept Internațional Umanitar",
          "type": "pdf"
        },
        {
          "date": "16-02-2023",
          "link": "https://www.mae.ro/sites/default/files/file/anul_2023/pdf_2023/2023.02.16_anexa_rof_cndiu.pdf",
          "title": "REGULAMENT DE FUNCŢIONARE",
          "type": "pdf"
        }
      ]
    },
    {
      "currentUrl": "https://www.mae.ro/node/2011",
      "date": "08-02-2023",
      "name": "LEGE privind declararea zilei de 3 martie Ziua solidarității româno-polone",
      "documents": [
        {
          "date": "08-02-2023",
          "link": "https://www.mae.ro/sites/default/files/file/anul_2023/pdf_2023/2023.02.08_lege_privind_declararea_zilei_de_3_martie_ziua_solidaritatii_romano-polone.pdf",
          "title": "LEGE privind declararea zilei de 3 martie Ziua solidarității româno-polone",
          "type": "pdf"
        },
        {
          "date": "08-02-2023",
          "link": "https://www.mae.ro/sites/default/files/file/anul_2023/pdf_2023/2023.02.08_expunere_de_motive_romano-polone_.pdf",
          "title": "EXPUNERE DE MOTIVE",
          "type": "pdf"
        }
      ]
    },
    {
      "currentUrl": "https://www.mae.ro/node/2011",
      "date": "01-02-2023",
      "name": "HOTĂRÂRE pentru aprobarea plății contribuției financiare voluntare a României la bugetul OCDE – Birou Ucraina",
      "documents": [
        {
          "date": "01-02-2023",
          "link": "https://www.mae.ro/sites/default/files/file/anul_2023/pdf_2023/2023.02.01_hg_ocde.pdf",
          "title": "HOTĂRÂRE pentru aprobarea plății contribuției financiare voluntare a României la bugetul OCDE – Birou Ucraina",
          "type": "pdf"
        },
        {
          "date": "01-02-2023",
          "link": "https://www.mae.ro/sites/default/files/file/anul_2023/pdf_2023/2023.02.01_nf_ocde.pdf",
          "title": "NOTĂ DE FUNDAMENTARE",
          "type": "pdf"
        }
      ]
    },
    {
      "currentUrl": "https://www.mae.ro/node/2011",
      "date": "30-01-2023",
      "name": "HOTĂRÂRE pentru aprobarea plății contribuției voluntare a României către următoarele Fonduri Voluntare ale Organizației Tratatului Atlanticului de Nord: Fondul voluntar de consolidare a capacității de apărare a Republicii Moldova (Moldova DCB Trust Fund) și Fondul voluntar privind Pachetul de Asistență Cuprinzătoare pentru Ucraina (NATO-Ukraine Comprehensive Assistance Package Trust Fund);",
      "documents": [
        {
          "date": "30-01-2023",
          "link": "https://www.mae.ro/sites/default/files/file/anul_2023/pdf_2023/2023.01.30_hg_redirectionare_contributie_ana_tf.pdf",
          "title": "HOTĂRÂRE pentru aprobarea plății contribuției voluntare a României către următoarele Fonduri Voluntare ale Organizației Tratatului Atlanticului de Nord: Fondul voluntar de consolidare a capacității de apărare a Republicii Moldova (Moldova DCB Trust Fund) și Fondul voluntar privind Pachetul de Asistență Cuprinzătoare pentru Ucraina (NATO-Ukraine Comprehensive Assistance Package Trust Fund);",
          "type": "pdf"
        },
        {
          "date": "30-01-2023",
          "link": "https://www.mae.ro/sites/default/files/file/anul_2023/pdf_2023/2023.01.30_nf_redirectionare_contributie_ana_tf.pdf",
          "title": "NOTĂ DE FUNDAMENTARE",
          "type": "pdf"
        }
      ]
    },
    {
      "currentUrl": "https://www.mae.ro/node/2011",
      "date": "18-01-2023",
      "name": "HOTĂRÂRE privind aprobarea plății contribuțiilor financiare voluntare ale României la unele proiecte ale Organizației pentru Securitate și Cooperare în Europa (OSCE)",
      "documents": [
        {
          "date": "18-01-2023",
          "link": "https://www.mae.ro/sites/default/files/file/anul_2023/pdf_2023/2023.01.18_proiect_hg_ref._proiecte_osce_pt._ua_si_rmd.pdf",
          "title": "HOTĂRÂRE privind aprobarea plății contribuțiilor financiare voluntare ale României la unele proiecte ale Organizației pentru Securitate și Cooperare în Europa (OSCE)",
          "type": "pdf"
        },
        {
          "date": "18-01-2023",
          "link": "https://www.mae.ro/sites/default/files/file/anul_2023/pdf_2023/2023.01.18_nf_proiecte_osce_pt._ua_si_rmd.pdf",
          "title": "NOTĂ DE FUNDAMENTARE",
          "type": "pdf"
        }
      ]
    }
  ]
}