{
  "mdezvoltarii": [
    {
      "currentUrl": "https://www.mdlpa.ro/pages/proiecthgstabilirelocuinteaplicarelegeanal",
      "date": "01-08-2023",
      "name": "Proiect de HG privind stabilirea regimului juridic al unor locuințe pentru tineri destinate închirierii, construite prin programe de investiţii la nivel naţional şi aflate în administrarea consiliilor locale, şi a măsurilor necesare în vederea aplicării prevederilor Legii nr. 152/1998 privind înființarea Agenției Naționale pentru Locuințe, referitoare la administrarea și vânzarea acestora",
      "documents": [
        {
          "date": "01-08-2023",
          "link": "https://www.mdlpa.ro/uploads/articole/attachments/64c90e9e9a3f6445652974.doc",
          "title": "Proiect HG",
          "type": "doc"
        },
        {
          "date": "01-08-2023",
          "link": "https://www.mdlpa.ro/uploads/articole/attachments/64c90e9c7bfd6734648970.doc",
          "title": "Anexă",
          "type": "doc"
        },
        {
          "date": "01-08-2023",
          "link": "https://www.mdlpa.ro/uploads/articole/attachments/64c90e9ddcb76799579886.doc",
          "title": "Nota de fundamentare",
          "type": "doc"
        }
      ]
    },
    {
      "currentUrl": "https://www.mdlpa.ro/pages/proiecthgnormeintocmireactualizaresistemelectronicnationalevidentaocuparesectorpublic27072023",
      "date": "27-07-2023",
      "name": "Proiect de HG privind normele referitoare la întocmirea, actualizarea și administrarea Sistemului electronic naţional de evidenţă a ocupării în sectorul public, precum şi detalierea operaţiunilor necesare completării bazei de date",
      "documents": [
        {
          "date": "27-07-2023",
          "link": "https://www.mdlpa.ro/uploads/articole/attachments/64c240714c798700790931.doc",
          "title": "Proiect HG",
          "type": "doc"
        },
        {
          "date": "27-07-2023",
          "link": "https://www.mdlpa.ro/uploads/articole/attachments/64c24074cb9d4467556889.doc",
          "title": "Nota de fundamentare",
          "type": "doc"
        },
        {
          "date": "27-07-2023",
          "link": "https://www.mdlpa.ro/uploads/articole/attachments/64c2405b49d1c045122724.doc",
          "title": "Anexa 1",
          "type": "doc"
        },
        {
          "date": "27-07-2023",
          "link": "https://www.mdlpa.ro/uploads/articole/attachments/64c2405d092f2883717309.doc",
          "title": "Anexa 2",
          "type": "doc"
        },
        {
          "date": "27-07-2023",
          "link": "https://www.mdlpa.ro/uploads/articole/attachments/64c2405e1ad93073991649.doc",
          "title": "Anexa 3",
          "type": "doc"
        },
        {
          "date": "27-07-2023",
          "link": "https://www.mdlpa.ro/uploads/articole/attachments/64c2405f190a8367826207.doc",
          "title": "Anexa 4",
          "type": "doc"
        },
        {
          "date": "27-07-2023",
          "link": "https://www.mdlpa.ro/uploads/articole/attachments/64c2411ed44d5536810364.doc",
          "title": "Anexa 5",
          "type": "doc"
        },
        {
          "date": "27-07-2023",
          "link": "https://www.mdlpa.ro/uploads/articole/attachments/64c241203f8cc953960249.doc",
          "title": "Anexa 6",
          "type": "doc"
        },
        {
          "date": "27-07-2023",
          "link": "https://www.mdlpa.ro/uploads/articole/attachments/64c2406c32fc6157093521.doc",
          "title": "Anexa 7",
          "type": "doc"
        }
      ]
    },
    {
      "currentUrl": "https://www.mdlpa.ro/pages/proiectougmodificarecodadministrativ27072023",
      "date": "27-07-2023",
      "name": "Proiect de OUG pentru modificarea și completarea Ordonanței de urgență a Guvernului nr. 57/2019 privind Codul administrativ",
      "documents": [
        {
          "date": "27-07-2023",
          "link": "https://www.mdlpa.ro/uploads/articole/attachments/64c23e99dc9e5174969439.doc",
          "title": "Proiect de Ordonanță de urgență",
          "type": "doc"
        },
        {
          "date": "27-07-2023",
          "link": "https://www.mdlpa.ro/uploads/articole/attachments/64c23e927c912979572165.doc",
          "title": "Nota de fundamentare",
          "type": "doc"
        },
        {
          "date": "27-07-2023",
          "link": "https://www.mdlpa.ro/uploads/articole/attachments/64c23e8d057e5618300792.doc",
          "title": "Anexa 10",
          "type": "doc"
        },
        {
          "date": "27-07-2023",
          "link": "https://www.mdlpa.ro/uploads/articole/attachments/64c23e9c0ef89184888625.doc",
          "title": "Tabel comparativ",
          "type": "doc"
        },
        {
          "date": "27-07-2023",
          "link": "https://www.mdlpa.ro/uploads/articole/attachments/64c23e8dc1167451020485.docx",
          "title": "Anexă la Tabelul comparativ",
          "type": "doc"
        }
      ]
    },
    {
      "currentUrl": "https://www.mdlpa.ro/pages/proiecthgmodificareanexahg9322007metodologiefinantarehartirisc",
      "date": "14-07-2023",
      "name": "Proiect de HG pentru modificarea anexei la Hotărârea Guvernului nr. 932/2007 pentru aprobarea Metodologiei privind finanțarea de la bugetul de stat a hărților de risc natural pentru cutremure și alunecări de teren",
      "documents": [
        {
          "date": "14-07-2023",
          "link": "https://www.mdlpa.ro/uploads/articole/attachments/64b12a9837de7380864465.doc",
          "title": "Proiect HG",
          "type": "doc"
        },
        {
          "date": "14-07-2023",
          "link": "https://www.mdlpa.ro/uploads/articole/attachments/64b12a99e0633237279362.doc",
          "title": "Nota de fundamentare",
          "type": "doc"
        }
      ]
    },
    {
      "currentUrl": "https://www.mdlpa.ro/pages/proiecthgaprobarenormemetodologicederulareprogramfinantarepug",
      "date": "30-06-2023",
      "name": "Proiect de HG privind aprobarea Normelor metodologice pentru derularea programului multianual privind finanțarea elaborării și/sau actualizării planurilor urbaniste generale ale localităților și a regulamentelor locale de urbanism",
      "documents": [
        {
          "date": "30-06-2023",
          "link": "https://www.mdlpa.ro/uploads/articole/attachments/649ec9a2d7ee6298870405.docx",
          "title": "Proiect HG",
          "type": "doc"
        },
        {
          "date": "30-06-2023",
          "link": "https://www.mdlpa.ro/uploads/articole/attachments/649ec9a144d18607032307.docx",
          "title": "Anexa 1",
          "type": "doc"
        },
        {
          "date": "30-06-2023",
          "link": "https://www.mdlpa.ro/uploads/articole/attachments/649ec9a1c3c26023805892.xlsx",
          "title": "Anexa 1.2",
          "type": "xls"
        },
        {
          "date": "30-06-2023",
          "link": "https://www.mdlpa.ro/uploads/articole/attachments/649ec9a1ae691860760763.xls",
          "title": "Anexa 2",
          "type": "xls"
        },
        {
          "date": "30-06-2023",
          "link": "https://www.mdlpa.ro/uploads/articole/attachments/649ec9a34a0d0999396545.docx",
          "title": "Nota de fundamentare",
          "type": "doc"
        }
      ]
    },
    {
      "currentUrl": "https://www.mdlpa.ro/pages/proiecthgmodifcarehg9072016documentatiitehnice",
      "date": "26-06-2023",
      "name": "Proiect de HG pentru modificarea și completarea Hotărârii Guvernului nr. 907/2016 privind etapele de elaborare și conținutul-cadru al documentațiilor tehnico-economice aferente obiectivelor/proiectelor de investiții finanțate din fonduri publice",
      "documents": [
        {
          "date": "26-06-2023",
          "link": "https://www.mdlpa.ro/uploads/articole/attachments/6499984391d0b043713429.doc",
          "title": "Proiect HG",
          "type": "doc"
        },
        {
          "date": "26-06-2023",
          "link": "https://www.mdlpa.ro/uploads/articole/attachments/64999842c98e1409507729.docx",
          "title": "Anexe 1-4",
          "type": "doc"
        },
        {
          "date": "26-06-2023",
          "link": "https://www.mdlpa.ro/uploads/articole/attachments/649998421d212696268050.xlsx",
          "title": "Anexa 7",
          "type": "xls"
        },
        {
          "date": "26-06-2023",
          "link": "https://www.mdlpa.ro/uploads/articole/attachments/649998441ce74764511046.docx",
          "title": "Nota de fundamentare",
          "type": "doc"
        }
      ]
    },
    {
      "currentUrl": "https://www.mdlpa.ro/pages/proiectordinaprobarecostunitarsuprafataobiectiveprogramconsolidarespitale",
      "date": "12-06-2023",
      "name": "Proiect de ORDIN al ministrului dezvoltării, lucrărilor publice și administrației pentru aprobarea costului unitar/mp suprafață desfășurată, pentru obiectivele de investiții care se realizează prin Programul național de investiții pentru consolidarea spitalelor „Mihail Cantacuzino”",
      "documents": [
        {
          "date": "12-06-2023",
          "link": "https://www.mdlpa.ro/uploads/articole/attachments/648733d32fe16842816370.doc",
          "title": "Proiect ordin",
          "type": "doc"
        },
        {
          "date": "12-06-2023",
          "link": "https://www.mdlpa.ro/uploads/articole/attachments/648733d39b199884328147.docx",
          "title": "Referat de aprobare",
          "type": "doc"
        }
      ]
    },
    {
      "currentUrl": "https://www.mdlpa.ro/pages/proiectougmodificareoug952021anghelsaligny",
      "date": "12-06-2023",
      "name": "Proiect de OUG pentru modificarea și completarea Ordonanței de urgență a Guvernului nr. 95/2021 pentru aprobarea Programului național de investiții „Anghel Saligny” și pentru instituirea unor măsuri în derularea Programului național de investiții „Anghel Saligny”",
      "documents": [
        {
          "date": "12-06-2023",
          "link": "https://www.mdlpa.ro/uploads/articole/attachments/648717487b261939698172.docx",
          "title": "Proiect de Ordonanță de urgență",
          "type": "doc"
        },
        {
          "date": "12-06-2023",
          "link": "https://www.mdlpa.ro/uploads/articole/attachments/648717480f889745640488.docx",
          "title": "Nota de fundamentare",
          "type": "doc"
        }
      ]
    },
    {
      "currentUrl": "https://www.mdlpa.ro/pages/proiectaprobarenormeoug492023",
      "date": "09-06-2023",
      "name": "Proiect de ORDIN al ministrului dezvoltării, lucrărilor publice și administrației pentru aprobarea Normelor metodologice de aplicare a prevederilor Ordonanței de urgență a Guvernului nr. 49/2023 privind aprobarea Programului național de investiții pentru consolidarea spitalelor „Mihail Cantacuzino” și a Programului național de expertizare a clădirilor publice cu risc seismic din sistemele de sănătate și de învățământ",
      "documents": [
        {
          "date": "09-06-2023",
          "link": "https://www.mdlpa.ro/uploads/articole/attachments/648302e748fed547389091.doc",
          "title": "Proiect ordin",
          "type": "doc"
        },
        {
          "date": "09-06-2023",
          "link": "https://www.mdlpa.ro/uploads/articole/attachments/648302e3a3dc0669147960.xlsx",
          "title": "Anexa 1",
          "type": "xls"
        },
        {
          "date": "09-06-2023",
          "link": "https://www.mdlpa.ro/uploads/articole/attachments/648302e42aa72257782612.docx",
          "title": "Anexa 2",
          "type": "doc"
        },
        {
          "date": "09-06-2023",
          "link": "https://www.mdlpa.ro/uploads/articole/attachments/648302e3c1b92181147084.docx",
          "title": "Anexa 2a",
          "type": "doc"
        },
        {
          "date": "09-06-2023",
          "link": "https://www.mdlpa.ro/uploads/articole/attachments/648302e33f14b986886341.docx",
          "title": "Anexa 3",
          "type": "doc"
        },
        {
          "date": "09-06-2023",
          "link": "https://www.mdlpa.ro/uploads/articole/attachments/648302e3244d1938201427.docx",
          "title": "Anexa 3a",
          "type": "doc"
        },
        {
          "date": "09-06-2023",
          "link": "https://www.mdlpa.ro/uploads/articole/attachments/648302e4b4788344843308.docx",
          "title": "Anexa 4",
          "type": "doc"
        },
        {
          "date": "09-06-2023",
          "link": "https://www.mdlpa.ro/uploads/articole/attachments/648302e449a96852072471.docx",
          "title": "Anexa 5",
          "type": "doc"
        },
        {
          "date": "09-06-2023",
          "link": "https://www.mdlpa.ro/uploads/articole/attachments/648302e4d01a4373682809.docx",
          "title": "Anexa 6",
          "type": "doc"
        },
        {
          "date": "09-06-2023",
          "link": "https://www.mdlpa.ro/uploads/articole/attachments/648302e6d0bc9747987770.doc",
          "title": "Norme",
          "type": "doc"
        },
        {
          "date": "09-06-2023",
          "link": "https://www.mdlpa.ro/uploads/articole/attachments/648302e809c79870624020.docx",
          "title": "Referat de aprobare",
          "type": "doc"
        }
      ]
    },
    {
      "currentUrl": "https://www.mdlpa.ro/pages/proiectordinaprobareregulamentgestionaresituatiicutremur",
      "date": "07-06-2023",
      "name": "Proiect de ORDIN pentru aprobarea Regulamentului privind gestionarea situaţiilor de urgenţă generate de cutremur",
      "documents": [
        {
          "date": "07-06-2023",
          "link": "https://www.mdlpa.ro/uploads/articole/attachments/64808c570f77b650247319.doc",
          "title": "Proiect Ordin",
          "type": "doc"
        },
        {
          "date": "07-06-2023",
          "link": "https://www.mdlpa.ro/uploads/articole/attachments/64808c58773b5855910246.doc",
          "title": "Referat de aprobare",
          "type": "doc"
        },
        {
          "date": "07-06-2023",
          "link": "https://www.mdlpa.ro/uploads/articole/attachments/64808c539425f971432401.DOCX",
          "title": "Regulament",
          "type": "doc"
        },
        {
          "date": "07-06-2023",
          "link": "https://www.mdlpa.ro/uploads/articole/attachments/64808c54005dd617442587.docx",
          "title": "Anexa 1",
          "type": "doc"
        },
        {
          "date": "07-06-2023",
          "link": "https://www.mdlpa.ro/uploads/articole/attachments/64808c540ec53577533606.docx",
          "title": "Anexa 2",
          "type": "doc"
        },
        {
          "date": "07-06-2023",
          "link": "https://www.mdlpa.ro/uploads/articole/attachments/64808c547199e063017437.docx",
          "title": "Anexa 3",
          "type": "doc"
        },
        {
          "date": "07-06-2023",
          "link": "https://www.mdlpa.ro/uploads/articole/attachments/64808c5482a98024578572.docx",
          "title": "Anexa 4",
          "type": "doc"
        },
        {
          "date": "07-06-2023",
          "link": "https://www.mdlpa.ro/uploads/articole/attachments/64808c54eeabe470083636.docx",
          "title": "Anexa 5",
          "type": "doc"
        },
        {
          "date": "07-06-2023",
          "link": "https://www.mdlpa.ro/uploads/articole/attachments/64808c561fa09442725632.docx",
          "title": "Anexa 6",
          "type": "doc"
        },
        {
          "date": "07-06-2023",
          "link": "https://www.mdlpa.ro/uploads/articole/attachments/64808c5683e04794155019.docx",
          "title": "Anexa 7",
          "type": "doc"
        }
      ]
    },
    {
      "currentUrl": "https://www.mdlpa.ro/pages/proiectordincompletareordin112110752014",
      "date": "29-05-2023",
      "name": "Proiect de ORDIN al ministrului dezvoltării, lucrărilor publice și administrației şi al ministrului finanţelor pentru modificarea și completarea Ordinului viceprim-ministrului, ministrul dezvoltării regionale şi administraţiei publice şi al ministrului delegat pentru buget nr. 1.121/1.075/2014 privind aprobarea Schemei de ajutor de stat acordat în perioada 2014 - 30 iunie 2023 operatorilor economici care prestează serviciul de interes economic general de producere, transport, distribuţie şi furnizare a energiei termice în sistem centralizat către populaţie",
      "documents": [
        {
          "date": "29-05-2023",
          "link": "https://www.mdlpa.ro/uploads/articole/attachments/6474b157634ad559954533.docx",
          "title": "Proiect ordin",
          "type": "doc"
        },
        {
          "date": "29-05-2023",
          "link": "https://www.mdlpa.ro/uploads/articole/attachments/6474b1f56abe3216581323.docx",
          "title": "Referat de aprobare",
          "type": "doc"
        }
      ]
    },
    {
      "currentUrl": "https://www.mdlpa.ro/pages/proiectordinaprobarereglementareghidrtc92023",
      "date": "19-05-2023",
      "name": "Proiect de ORDIN privind aprobarea reglementării tehnice „Ghid privind utilizarea instrumentelor BIM în generarea și gestionarea datelor digitale aferente construcțiilor, indicativ RTC 9 - 2023”",
      "documents": [
        {
          "date": "19-05-2023",
          "link": "https://www.mdlpa.ro/uploads/articole/attachments/6467610231f62895788029.doc",
          "title": "Proiect ordin",
          "type": "doc"
        },
        {
          "date": "19-05-2023",
          "link": "https://www.mdlpa.ro/uploads/articole/attachments/646c55817ac3d543591653.docx",
          "title": "Anexă: RTC 9 - GHID PRIVIND UTILIZAREA INSTRUMENTELOR DE GENERARE ȘI GESTIONARE A DATELOR DIGITALE AFERENTE CONSTRUCȚIILOR",
          "type": "doc"
        },
        {
          "date": "19-05-2023",
          "link": "https://www.mdlpa.ro/uploads/articole/attachments/646761a83dd78790342988.doc",
          "title": "Referat de aprobare",
          "type": "doc"
        }
      ]
    },
    {
      "currentUrl": "https://www.mdlpa.ro/pages/proiectordinaprobarereglementaretehnicartc82023",
      "date": "19-05-2023",
      "name": "Proiect de ORDIN privind aprobarea reglementării tehnice „Ghid privind managementul și monitorizarea informațiilor generate în sistem BIM, indicativ RTC 8 - 2023”",
      "documents": [
        {
          "date": "19-05-2023",
          "link": "https://www.mdlpa.ro/uploads/articole/attachments/646752c58c023240138534.doc",
          "title": "Proiect ordin",
          "type": "doc"
        },
        {
          "date": "19-05-2023",
          "link": "https://www.mdlpa.ro/uploads/articole/attachments/646b678570c34662386677.docx",
          "title": "Anexă: RTC 8 - GHID PRIVIND MANAGEMENTUL ȘI MONITORIZAREA INFORMAȚIILOR GENERATE ÎN SISTEM BIM",
          "type": "doc"
        },
        {
          "date": "19-05-2023",
          "link": "https://www.mdlpa.ro/uploads/articole/attachments/646752e2d4ba0057498916.doc",
          "title": "Referat de aprobare",
          "type": "doc"
        }
      ]
    },
    {
      "currentUrl": "https://www.mdlpa.ro/pages/proiectordinmodificarenormeoug952021anghelsaligny",
      "date": "04-04-2023",
      "name": "Proiect de ORDIN privind modificarea Normelor metodologice pentru punerea în aplicare a prevederilor Ordonanţei de urgenţă a Guvernului nr. 95/2021 pentru aprobarea Programului național de investiţii \"Anghel Saligny\", pentru categoriile de investiții prevăzute la art. 4 alin. (1) lit. a)-d) din Ordonanţa de urgenţă a Guvernului nr. 95/2021, aprobate prin Ordinul  ministrului dezvoltării, lucrărilor publice și administrației nr. 1333/2021",
      "documents": [
        {
          "date": "04-04-2023",
          "link": "https://www.mdlpa.ro/uploads/articole/attachments/642bdbbb963f6217401912.doc",
          "title": "Proiect Ordin",
          "type": "doc"
        },
        {
          "date": "04-04-2023",
          "link": "https://www.mdlpa.ro/uploads/articole/attachments/642bdbbba3f94405119226.docx",
          "title": "Referat de aprobare",
          "type": "doc"
        }
      ]
    },
    {
      "currentUrl": "https://www.mdlpa.ro/pages/proiectordinmodificarecompletarenormeoug952021anghelsaligny",
      "date": "30-03-2023",
      "name": "Proiect de ORDIN privind modificarea și completarea Normelor metodologice pentru punerea în aplicare a prevederilor Ordonanţei de urgenţă a Guvernului nr. 95/2021 pentru aprobarea Programului național de investiţii \"Anghel Saligny\", pentru categoria de investiții prevăzută la art. 4 alin. (1) lit. e) din Ordonanţa de urgenţă a Guvernului nr. 95/2021, aprobate prin Ordinul comun al ministrului dezvoltării, lucrărilor publice și administrației și al ministrului energiei nr. 278/167/2022 și pentru instituirea unor măsuri privind derularea Programului național de investiții „Anghel Saligny”",
      "documents": [
        {
          "date": "30-03-2023",
          "link": "https://www.mdlpa.ro/uploads/articole/attachments/64254aaba5854931652764.doc",
          "title": "Proiect Ordin",
          "type": "doc"
        },
        {
          "date": "30-03-2023",
          "link": "https://www.mdlpa.ro/uploads/articole/attachments/64254a916f640874377244.docx",
          "title": "Anexa 1",
          "type": "doc"
        },
        {
          "date": "30-03-2023",
          "link": "https://www.mdlpa.ro/uploads/articole/attachments/64254a9b18a49131334854.docx",
          "title": "Anexa 2",
          "type": "doc"
        },
        {
          "date": "30-03-2023",
          "link": "https://www.mdlpa.ro/uploads/articole/attachments/64254aab9540f797033452.docx",
          "title": "Anexa 3",
          "type": "doc"
        },
        {
          "date": "30-03-2023",
          "link": "https://www.mdlpa.ro/uploads/articole/attachments/64254aabb2ed2706866557.docx",
          "title": "Referat de aprobare",
          "type": "doc"
        }
      ]
    },
    {
      "currentUrl": "https://www.mdlpa.ro/pages/proiectougstabiliremasuriprogramanghelsaligny",
      "date": "28-03-2023",
      "name": "Proiect de OUG privind stabilirea unor măsuri în derularea Programului național de investiții „Anghel Saligny”",
      "documents": [
        {
          "date": "28-03-2023",
          "link": "https://www.mdlpa.ro/uploads/articole/attachments/64230fcf00cef757022474.docx",
          "title": "Proiect de Ordonanță de urgență",
          "type": "doc"
        },
        {
          "date": "28-03-2023",
          "link": "https://www.mdlpa.ro/uploads/articole/attachments/64230fdfeebca534365727.docx",
          "title": "Nota de fundamentare",
          "type": "doc"
        }
      ]
    },
    {
      "currentUrl": "https://www.mdlpa.ro/pages/proiecthgmodificarenormeaplicarelegealocuintei1141996",
      "date": "21-03-2023",
      "name": "Proiect de HG pentru modificarea și completarea Normelor metodologice pentru punerea în aplicare a prevederilor Legii locuinței nr. 114/1996, aprobate prin Hotărârea Guvernului nr. 1.275/2000",
      "documents": [
        {
          "date": "21-03-2023",
          "link": "https://www.mdlpa.ro/uploads/articole/attachments/6419aafbdee3f456650954.doc",
          "title": "Proiect HG",
          "type": "doc"
        },
        {
          "date": "21-03-2023",
          "link": "https://www.mdlpa.ro/uploads/articole/attachments/6419aafbc6274277034735.docx",
          "title": "Anexa 1",
          "type": "doc"
        },
        {
          "date": "21-03-2023",
          "link": "https://www.mdlpa.ro/uploads/articole/attachments/6419aafbb96cd516888313.docx",
          "title": "Anexa 2",
          "type": "doc"
        },
        {
          "date": "21-03-2023",
          "link": "https://www.mdlpa.ro/uploads/articole/attachments/6419aafbabc5f147027223.docx",
          "title": "Anexa 3",
          "type": "doc"
        },
        {
          "date": "21-03-2023",
          "link": "https://www.mdlpa.ro/uploads/articole/attachments/6419aafbeab95697004034.docx",
          "title": "Nota de fundamentare",
          "type": "doc"
        }
      ]
    }
  ]
}